[
    {
        "name": "شبندر3",
        "queue_order_count": 5631,
        "total_queue_value": 610.7,
        "solid": true,
        "growth": 1.25,
        "demand_ratio": 145.3,
        "vol_ratio": 0.11,
        "market": 471.6,
        "group": "فراورده های نفتی، کک و سوخت هسته ای",
        "pe_ttm": 5.4,
        "chance": 0.01,
        "days_lock": 6,
        "base_vol_percent": 100,
        "recent_growth": 1.29,
        "buy_power": 2.8,
        "each_person_buy": 113,
        "free_float_share": 30,
        "order_value": 115,
        "ath_diff": null,
        "expected_days": 1320.9,
        "buy_to_failure": 47
    },
    {
        "name": "ذرت",
        "queue_order_count": 5148,
        "total_queue_value": 131.3,
        "solid": true,
        "growth": 1.11,
        "demand_ratio": 6.6,
        "vol_ratio": 1.16,
        "market": 4.3,
        "group": "محصولات غذایی و آشامیدنی به جز قند و شکر",
        "pe_ttm": 6.8,
        "chance": 0.03,
        "days_lock": 2,
        "base_vol_percent": 100,
        "recent_growth": 18.79,
        "buy_power": 204.4,
        "each_person_buy": 45,
        "free_float_share": 10,
        "order_value": 187,
        "ath_diff": null,
        "expected_days": 5.7,
        "buy_to_failure": 7
    },
    {
        "name": "زهلال",
        "queue_order_count": 4146,
        "total_queue_value": 106.0,
        "solid": true,
        "growth": 1.14,
        "demand_ratio": 8.6,
        "vol_ratio": 0.94,
        "market": 2.0,
        "group": "زراعت و خدمات وابسته",
        "pe_ttm": 6.8,
        "chance": 0.03,
        "days_lock": 3,
        "base_vol_percent": 100,
        "recent_growth": 39.8,
        "buy_power": 297.1,
        "each_person_buy": 39,
        "free_float_share": 13,
        "order_value": 398,
        "ath_diff": null,
        "expected_days": 9.1,
        "buy_to_failure": 15
    },
    {
        "name": "حکشتی",
        "queue_order_count": 3782,
        "total_queue_value": 401.1,
        "solid": true,
        "growth": 1.27,
        "demand_ratio": 25.6,
        "vol_ratio": 7.97,
        "market": 77.3,
        "group": "حمل ونقل، انبارداری و ارتباطات",
        "pe_ttm": 4.5,
        "chance": 0.07,
        "days_lock": 3,
        "base_vol_percent": 100,
        "recent_growth": 1.16,
        "buy_power": 13.1,
        "each_person_buy": 145,
        "free_float_share": 29,
        "order_value": 133,
        "ath_diff": null,
        "expected_days": 3.2,
        "buy_to_failure": 10
    },
    {
        "name": "رمپنا",
        "queue_order_count": 3245,
        "total_queue_value": 519.1,
        "solid": true,
        "growth": 1.68,
        "demand_ratio": 7.6,
        "vol_ratio": 2.1,
        "market": 109.9,
        "group": "خدمات فنی و مهندسی",
        "pe_ttm": 2.6,
        "chance": 0.07,
        "days_lock": 12,
        "base_vol_percent": 100,
        "recent_growth": 1.47,
        "buy_power": 3.8,
        "each_person_buy": 188,
        "free_float_share": 30,
        "order_value": 183,
        "ath_diff": null,
        "expected_days": 3.6,
        "buy_to_failure": 14
    },
    {
        "name": "وفیروزه",
        "queue_order_count": 3041,
        "total_queue_value": 230.4,
        "solid": true,
        "growth": 1.27,
        "demand_ratio": 8.0,
        "vol_ratio": 1.73,
        "market": 6.3,
        "group": "سرمایه گذاریها",
        "pe_ttm": 8.2,
        "chance": 0.04,
        "days_lock": 9,
        "base_vol_percent": 100,
        "recent_growth": 3.51,
        "buy_power": 374.6,
        "each_person_buy": 129,
        "free_float_share": 11,
        "order_value": 140,
        "ath_diff": null,
        "expected_days": 4.6,
        "buy_to_failure": 6
    },
    {
        "name": "شپنا3",
        "queue_order_count": 3004,
        "total_queue_value": 516.8,
        "solid": true,
        "growth": 1.33,
        "demand_ratio": 3742.5,
        "vol_ratio": 1.02,
        "market": 587.7,
        "group": "فراورده های نفتی، کک و سوخت هسته ای",
        "pe_ttm": 6.3,
        "chance": 0.0,
        "days_lock": 3,
        "base_vol_percent": 100,
        "recent_growth": 1.32,
        "buy_power": 4.5,
        "each_person_buy": 71,
        "free_float_share": 34,
        "order_value": 187,
        "ath_diff": null,
        "expected_days": 3669.1,
        "buy_to_failure": 0
    },
    {
        "name": "ونوین3",
        "queue_order_count": 2788,
        "total_queue_value": 386.2,
        "solid": true,
        "growth": 1.19,
        "demand_ratio": 502.9,
        "vol_ratio": 0.05,
        "market": 87.9,
        "group": "بانکها و موسسات اعتباری",
        "pe_ttm": 4.7,
        "chance": 0.0,
        "days_lock": 3,
        "base_vol_percent": 100,
        "recent_growth": 1.22,
        "buy_power": 2.0,
        "each_person_buy": 37,
        "free_float_share": 32,
        "order_value": 144,
        "ath_diff": null,
        "expected_days": 10058.0,
        "buy_to_failure": 0
    },
    {
        "name": "تادیکو",
        "queue_order_count": 2683,
        "total_queue_value": 168.4,
        "solid": true,
        "growth": 1.16,
        "demand_ratio": 5.3,
        "vol_ratio": 1.31,
        "market": 11.0,
        "group": "زراعت و خدمات وابسته",
        "pe_ttm": 23.2,
        "chance": 0.03,
        "days_lock": 6,
        "base_vol_percent": 100,
        "recent_growth": 7.32,
        "buy_power": 276.0,
        "each_person_buy": 128,
        "free_float_share": 6,
        "order_value": 146,
        "ath_diff": null,
        "expected_days": 4.0,
        "buy_to_failure": 5
    },
    {
        "name": "شپنا",
        "queue_order_count": 2207,
        "total_queue_value": 263.1,
        "solid": false,
        "growth": 3.2,
        "demand_ratio": 0.4,
        "vol_ratio": 3.06,
        "market": 589.0,
        "group": "فراورده های نفتی، کک و سوخت هسته ای",
        "pe_ttm": 6.3,
        "chance": 7.38,
        "days_lock": 10,
        "base_vol_percent": 100,
        "recent_growth": 1.82,
        "buy_power": -1.1,
        "each_person_buy": 178,
        "free_float_share": 34,
        "order_value": 187,
        "ath_diff": null,
        "expected_days": 0.1,
        "buy_to_failure": 0
    },
    {
        "name": "وتجارت3",
        "queue_order_count": 2068,
        "total_queue_value": 51.0,
        "solid": true,
        "growth": 1.23,
        "demand_ratio": 291.8,
        "vol_ratio": 0.22,
        "market": 100.5,
        "group": "بانکها و موسسات اعتباری",
        "pe_ttm": 4.0,
        "chance": 0.12,
        "days_lock": 4,
        "base_vol_percent": 100,
        "recent_growth": 1.2,
        "buy_power": 1.7,
        "each_person_buy": 13,
        "free_float_share": 47,
        "order_value": 25,
        "ath_diff": null,
        "expected_days": 1326.4,
        "buy_to_failure": 122
    },
    {
        "name": "تاپیکو3",
        "queue_order_count": 1938,
        "total_queue_value": 453.2,
        "solid": true,
        "growth": 1.24,
        "demand_ratio": 2903.1,
        "vol_ratio": 0.01,
        "market": 261.9,
        "group": "محصولات شیمیایی",
        "pe_ttm": 12.3,
        "chance": 0.0,
        "days_lock": 3,
        "base_vol_percent": 100,
        "recent_growth": 1.36,
        "buy_power": -1.0,
        "each_person_buy": 1,
        "free_float_share": 11,
        "order_value": 258,
        "ath_diff": null,
        "expected_days": 290310.0,
        "buy_to_failure": 0
    },
    {
        "name": "شستا3",
        "queue_order_count": 1637,
        "total_queue_value": 127.8,
        "solid": true,
        "growth": 1.23,
        "demand_ratio": 7.6,
        "vol_ratio": 0.01,
        "market": 343.4,
        "group": "شرکتهای چند رشته ای صنعتی",
        "pe_ttm": 11.1,
        "chance": 0.02,
        "days_lock": 8,
        "base_vol_percent": 100,
        "recent_growth": 1.2,
        "buy_power": 5.5,
        "each_person_buy": 66,
        "free_float_share": 12,
        "order_value": 83,
        "ath_diff": null,
        "expected_days": 760.0,
        "buy_to_failure": 40
    },
    {
        "name": "دعبید",
        "queue_order_count": 1347,
        "total_queue_value": 169.8,
        "solid": true,
        "growth": 2.26,
        "demand_ratio": 1.7,
        "vol_ratio": 0.24,
        "market": 82.7,
        "group": "مواد و محصولات دارویی",
        "pe_ttm": 13.6,
        "chance": 0.92,
        "days_lock": 22,
        "base_vol_percent": 100,
        "recent_growth": 1.81,
        "buy_power": 1.8,
        "each_person_buy": 189,
        "free_float_share": 11,
        "order_value": 147,
        "ath_diff": null,
        "expected_days": 7.1,
        "buy_to_failure": 0
    },
    {
        "name": "فارس3",
        "queue_order_count": 1284,
        "total_queue_value": 152.7,
        "solid": true,
        "growth": 1.11,
        "demand_ratio": 11.1,
        "vol_ratio": 21.82,
        "market": 1281.0,
        "group": "محصولات شیمیایی",
        "pe_ttm": 6.7,
        "chance": 33.21,
        "days_lock": 5,
        "base_vol_percent": 100,
        "recent_growth": 1.23,
        "buy_power": 52.6,
        "each_person_buy": 774,
        "free_float_share": 33,
        "order_value": 128,
        "ath_diff": null,
        "expected_days": 0.5,
        "buy_to_failure": 0
    },
    {
        "name": "خودکفا",
        "queue_order_count": 1168,
        "total_queue_value": 178.9,
        "solid": true,
        "growth": 1.87,
        "demand_ratio": 193.2,
        "vol_ratio": 2.84,
        "market": 8.4,
        "group": "محصولات غذایی و آشامیدنی به جز قند و شکر",
        "pe_ttm": 4.9,
        "chance": 0.0,
        "days_lock": 12,
        "base_vol_percent": 8,
        "recent_growth": 1.28,
        "buy_power": 4.9,
        "each_person_buy": 137,
        "free_float_share": 72,
        "order_value": 167,
        "ath_diff": null,
        "expected_days": 68.0,
        "buy_to_failure": 0
    },
    {
        "name": "ونفت",
        "queue_order_count": 1087,
        "total_queue_value": 83.2,
        "solid": true,
        "growth": 1.7,
        "demand_ratio": 10.8,
        "vol_ratio": 3.09,
        "market": 3.3,
        "group": "فراورده های نفتی، کک و سوخت هسته ای",
        "pe_ttm": 1.7,
        "chance": 0.05,
        "days_lock": 3,
        "base_vol_percent": 100,
        "recent_growth": 1.34,
        "buy_power": 6.1,
        "each_person_buy": 109,
        "free_float_share": 41,
        "order_value": 111,
        "ath_diff": null,
        "expected_days": 3.5,
        "buy_to_failure": 6
    },
    {
        "name": "شتران3",
        "queue_order_count": 911,
        "total_queue_value": 77.7,
        "solid": true,
        "growth": 1.2,
        "demand_ratio": 5.5,
        "vol_ratio": 0.0,
        "market": 336.7,
        "group": "فراورده های نفتی، کک و سوخت هسته ای",
        "pe_ttm": 4.1,
        "chance": 0.01,
        "days_lock": 8,
        "base_vol_percent": 100,
        "recent_growth": 1.2,
        "buy_power": 12.0,
        "each_person_buy": 54,
        "free_float_share": 50,
        "order_value": 103,
        "ath_diff": null,
        "expected_days": 1,
        "buy_to_failure": 1
    },
    {
        "name": "غشهداب",
        "queue_order_count": 887,
        "total_queue_value": 87.6,
        "solid": true,
        "growth": 1.46,
        "demand_ratio": 12.4,
        "vol_ratio": 2.81,
        "market": 1.8,
        "group": "محصولات غذایی و آشامیدنی به جز قند و شکر",
        "pe_ttm": 5.6,
        "chance": 0.04,
        "days_lock": 14,
        "base_vol_percent": 100,
        "recent_growth": 1.5,
        "buy_power": 6.6,
        "each_person_buy": 120,
        "free_float_share": 45,
        "order_value": 65,
        "ath_diff": null,
        "expected_days": 4.4,
        "buy_to_failure": 3
    },
    {
        "name": "توسن",
        "queue_order_count": 869,
        "total_queue_value": 145.3,
        "solid": true,
        "growth": 1.75,
        "demand_ratio": 11.2,
        "vol_ratio": 3.0,
        "market": 4.1,
        "group": "رایانه و فعالیتهای وابسته به آن",
        "pe_ttm": 2.7,
        "chance": 0.09,
        "days_lock": 20,
        "base_vol_percent": 100,
        "recent_growth": 1.8,
        "buy_power": 14.7,
        "each_person_buy": 197,
        "free_float_share": 31,
        "order_value": 108,
        "ath_diff": null,
        "expected_days": 3.7,
        "buy_to_failure": 11
    },
    {
        "name": "درازک",
        "queue_order_count": 819,
        "total_queue_value": 48.2,
        "solid": true,
        "growth": 2.04,
        "demand_ratio": 48.8,
        "vol_ratio": 10.14,
        "market": 3.0,
        "group": "مواد و محصولات دارویی",
        "pe_ttm": 11.3,
        "chance": 0.03,
        "days_lock": 6,
        "base_vol_percent": 100,
        "recent_growth": 1.19,
        "buy_power": 6.5,
        "each_person_buy": 66,
        "free_float_share": 29,
        "order_value": 69,
        "ath_diff": null,
        "expected_days": 4.8,
        "buy_to_failure": 2
    },
    {
        "name": "اخابر3",
        "queue_order_count": 809,
        "total_queue_value": 21.0,
        "solid": true,
        "growth": 1.26,
        "demand_ratio": 4.4,
        "vol_ratio": 0.0,
        "market": 64.5,
        "group": "مخابرات",
        "pe_ttm": 5.6,
        "chance": 0.0,
        "days_lock": 8,
        "base_vol_percent": 100,
        "recent_growth": 1.24,
        "buy_power": -1.0,
        "each_person_buy": 1,
        "free_float_share": 29,
        "order_value": 26,
        "ath_diff": null,
        "expected_days": 1,
        "buy_to_failure": 0
    },
    {
        "name": "اخابر",
        "queue_order_count": 730,
        "total_queue_value": 18.2,
        "solid": false,
        "growth": 1.85,
        "demand_ratio": 0.3,
        "vol_ratio": 2.08,
        "market": 65.6,
        "group": "مخابرات",
        "pe_ttm": 5.7,
        "chance": 37.29,
        "days_lock": 3,
        "base_vol_percent": 100,
        "recent_growth": 1.59,
        "buy_power": 1.8,
        "each_person_buy": 99,
        "free_float_share": 29,
        "order_value": 27,
        "ath_diff": null,
        "expected_days": 0.1,
        "buy_to_failure": 0
    },
    {
        "name": "شبریز3",
        "queue_order_count": 725,
        "total_queue_value": 264.3,
        "solid": true,
        "growth": 1.26,
        "demand_ratio": 4836.1,
        "vol_ratio": 0.68,
        "market": 131.5,
        "group": "فراورده های نفتی، کک و سوخت هسته ای",
        "pe_ttm": 5.2,
        "chance": 0.0,
        "days_lock": 3,
        "base_vol_percent": 100,
        "recent_growth": 1.23,
        "buy_power": 2.0,
        "each_person_buy": 37,
        "free_float_share": 29,
        "order_value": 438,
        "ath_diff": null,
        "expected_days": 7111.9,
        "buy_to_failure": 0
    },
    {
        "name": "وبملت3",
        "queue_order_count": 694,
        "total_queue_value": 24.2,
        "solid": true,
        "growth": 1.1,
        "demand_ratio": 1.1,
        "vol_ratio": 0.03,
        "market": 437.3,
        "group": "بانکها و موسسات اعتباری",
        "pe_ttm": 1.7,
        "chance": 0.92,
        "days_lock": 7,
        "base_vol_percent": 100,
        "recent_growth": 1.12,
        "buy_power": 2.9,
        "each_person_buy": 40,
        "free_float_share": 48,
        "order_value": 51,
        "ath_diff": null,
        "expected_days": 36.7,
        "buy_to_failure": 0
    },
    {
        "name": "حتاید",
        "queue_order_count": 694,
        "total_queue_value": 86.6,
        "solid": true,
        "growth": 1.46,
        "demand_ratio": 1.6,
        "vol_ratio": 1.89,
        "market": 18.0,
        "group": "حمل ونقل، انبارداری و ارتباطات",
        "pe_ttm": 6.2,
        "chance": 0.56,
        "days_lock": 12,
        "base_vol_percent": 100,
        "recent_growth": 1.33,
        "buy_power": 1.9,
        "each_person_buy": 252,
        "free_float_share": 99,
        "order_value": 164,
        "ath_diff": null,
        "expected_days": 0.8,
        "buy_to_failure": 94
    },
    {
        "name": "شغدیر",
        "queue_order_count": 673,
        "total_queue_value": 150.0,
        "solid": true,
        "growth": 1.27,
        "demand_ratio": 84.3,
        "vol_ratio": 0.47,
        "market": 4.3,
        "group": "محصولات شیمیایی",
        "pe_ttm": 6.5,
        "chance": 0.0,
        "days_lock": 7,
        "base_vol_percent": 100,
        "recent_growth": 1.23,
        "buy_power": 23.6,
        "each_person_buy": 279,
        "free_float_share": 22,
        "order_value": 329,
        "ath_diff": null,
        "expected_days": 179.4,
        "buy_to_failure": 0
    },
    {
        "name": "دارو",
        "queue_order_count": 657,
        "total_queue_value": 73.6,
        "solid": true,
        "growth": 3.3,
        "demand_ratio": 11.9,
        "vol_ratio": 0.73,
        "market": 21.0,
        "group": "مواد و محصولات دارویی",
        "pe_ttm": 7.8,
        "chance": 0.02,
        "days_lock": 21,
        "base_vol_percent": 100,
        "recent_growth": 1.69,
        "buy_power": 5.0,
        "each_person_buy": 148,
        "free_float_share": 11,
        "order_value": 162,
        "ath_diff": null,
        "expected_days": 16.3,
        "buy_to_failure": 5
    },
    {
        "name": "غبشهر",
        "queue_order_count": 602,
        "total_queue_value": 67.9,
        "solid": true,
        "growth": 3.84,
        "demand_ratio": 36.4,
        "vol_ratio": 0.45,
        "market": 23.8,
        "group": "محصولات غذایی و آشامیدنی به جز قند و شکر",
        "pe_ttm": 14.9,
        "chance": 0.01,
        "days_lock": 22,
        "base_vol_percent": 100,
        "recent_growth": 1.85,
        "buy_power": 11.6,
        "each_person_buy": 118,
        "free_float_share": 13,
        "order_value": 135,
        "ath_diff": null,
        "expected_days": 80.9,
        "buy_to_failure": 5
    },
    {
        "name": "دجابر",
        "queue_order_count": 598,
        "total_queue_value": 76.9,
        "solid": true,
        "growth": 1.88,
        "demand_ratio": 19.6,
        "vol_ratio": 2.7,
        "market": 3.3,
        "group": "مواد و محصولات دارویی",
        "pe_ttm": 9.3,
        "chance": 0.07,
        "days_lock": 20,
        "base_vol_percent": 100,
        "recent_growth": 1.79,
        "buy_power": 20.4,
        "each_person_buy": 145,
        "free_float_share": 23,
        "order_value": 145,
        "ath_diff": null,
        "expected_days": 7.3,
        "buy_to_failure": 12
    },
    {
        "name": "هجرت",
        "queue_order_count": 563,
        "total_queue_value": 89.7,
        "solid": true,
        "growth": 3.06,
        "demand_ratio": 16.6,
        "vol_ratio": 1.23,
        "market": 10.4,
        "group": "مواد و محصولات دارویی",
        "pe_ttm": 8.5,
        "chance": 0.03,
        "days_lock": 21,
        "base_vol_percent": 100,
        "recent_growth": 1.85,
        "buy_power": 3.8,
        "each_person_buy": 190,
        "free_float_share": 22,
        "order_value": 100,
        "ath_diff": null,
        "expected_days": 13.5,
        "buy_to_failure": 4
    },
    {
        "name": "پاریز",
        "queue_order_count": 562,
        "total_queue_value": 20.8,
        "solid": false,
        "growth": 1.24,
        "demand_ratio": 0.5,
        "vol_ratio": 3.51,
        "market": 6.7,
        "group": "انبوه سازی، املاک و مستغلات",
        "pe_ttm": 40.7,
        "chance": 1.38,
        "days_lock": 6,
        "base_vol_percent": 100,
        "recent_growth": 33.5,
        "buy_power": 49.5,
        "each_person_buy": 47,
        "free_float_share": 13,
        "order_value": 335,
        "ath_diff": null,
        "expected_days": 0.1,
        "buy_to_failure": 0
    },
    {
        "name": "پالایش",
        "queue_order_count": 539,
        "total_queue_value": 176.3,
        "solid": false,
        "growth": 3.08,
        "demand_ratio": 0.7,
        "vol_ratio": 4.77,
        "market": 59.5,
        "group": "صندوق سرمایه گذاری قابل معامله",
        "pe_ttm": 0.0,
        "chance": 2341.37,
        "days_lock": 8,
        "base_vol_percent": 100,
        "recent_growth": 1.68,
        "buy_power": 1.7,
        "each_person_buy": 448,
        "free_float_share": 43,
        "order_value": 2246,
        "ath_diff": null,
        "expected_days": 0.1,
        "buy_to_failure": 0
    },
    {
        "name": "سامان3",
        "queue_order_count": 508,
        "total_queue_value": 108.0,
        "solid": true,
        "growth": 1.27,
        "demand_ratio": 26.3,
        "vol_ratio": 0.01,
        "market": 89.9,
        "group": "بانکها و موسسات اعتباری",
        "pe_ttm": 4.8,
        "chance": 0.0,
        "days_lock": 5,
        "base_vol_percent": 100,
        "recent_growth": 1.31,
        "buy_power": 2.0,
        "each_person_buy": 23,
        "free_float_share": 56,
        "order_value": 113,
        "ath_diff": null,
        "expected_days": 2630.0,
        "buy_to_failure": 0
    },
    {
        "name": "خودرو3",
        "queue_order_count": 474,
        "total_queue_value": 8.3,
        "solid": true,
        "growth": 1.13,
        "demand_ratio": 0.3,
        "vol_ratio": 0.01,
        "market": 145.4,
        "group": "خودرو و ساخت قطعات",
        "pe_ttm": -6.8,
        "chance": 2.67,
        "days_lock": 9,
        "base_vol_percent": 100,
        "recent_growth": 1.12,
        "buy_power": 2.0,
        "each_person_buy": 18,
        "free_float_share": 24,
        "order_value": 22,
        "ath_diff": null,
        "expected_days": 30.0,
        "buy_to_failure": 0
    },
    {
        "name": "سرود3",
        "queue_order_count": 468,
        "total_queue_value": 55.6,
        "solid": false,
        "growth": 0.99,
        "demand_ratio": 9855.6,
        "vol_ratio": 0.0,
        "market": 13.2,
        "group": "سیمان، آهک و گچ",
        "pe_ttm": 7.5,
        "chance": 0.0,
        "days_lock": 1,
        "base_vol_percent": 100,
        "recent_growth": 1.02,
        "buy_power": 0,
        "each_person_buy": 0,
        "free_float_share": 42,
        "order_value": 137,
        "ath_diff": null,
        "expected_days": 1,
        "buy_to_failure": 0
    },
    {
        "name": "غکورش",
        "queue_order_count": 457,
        "total_queue_value": 32.3,
        "solid": false,
        "growth": 5.63,
        "demand_ratio": 1.2,
        "vol_ratio": 4.96,
        "market": 74.0,
        "group": "محصولات غذایی و آشامیدنی به جز قند و شکر",
        "pe_ttm": 13.6,
        "chance": 4.75,
        "days_lock": 26,
        "base_vol_percent": 100,
        "recent_growth": 1.95,
        "buy_power": -1.3,
        "each_person_buy": 91,
        "free_float_share": 8,
        "order_value": 168,
        "ath_diff": null,
        "expected_days": 0.2,
        "buy_to_failure": 0
    },
    {
        "name": "خساپا3",
        "queue_order_count": 456,
        "total_queue_value": 9.3,
        "solid": true,
        "growth": 1.12,
        "demand_ratio": 1.0,
        "vol_ratio": 0.02,
        "market": 92.7,
        "group": "خودرو و ساخت قطعات",
        "pe_ttm": -6.9,
        "chance": 1.75,
        "days_lock": 12,
        "base_vol_percent": 100,
        "recent_growth": 1.1,
        "buy_power": -1.4,
        "each_person_buy": 21,
        "free_float_share": 22,
        "order_value": 22,
        "ath_diff": null,
        "expected_days": 50.0,
        "buy_to_failure": 0
    },
    {
        "name": "آسال",
        "queue_order_count": 425,
        "total_queue_value": 0.7,
        "solid": true,
        "growth": 1.0,
        "demand_ratio": 0.0,
        "vol_ratio": 1.84,
        "market": 1.0,
        "group": "صندوق سرمایه گذاری قابل معامله",
        "pe_ttm": 714.4,
        "chance": 17283.61,
        "days_lock": 2,
        "base_vol_percent": 100,
        "recent_growth": 1.0,
        "buy_power": 0,
        "each_person_buy": 3,
        "free_float_share": 2,
        "order_value": 100,
        "ath_diff": null,
        "expected_days": 0.0,
        "buy_to_failure": 0
    },
    {
        "name": "غپینو3",
        "queue_order_count": 397,
        "total_queue_value": 21.0,
        "solid": true,
        "growth": 1.0,
        "demand_ratio": 18468.1,
        "vol_ratio": 0.66,
        "market": 16.5,
        "group": "محصولات غذایی و آشامیدنی به جز قند و شکر",
        "pe_ttm": 7.7,
        "chance": 0.0,
        "days_lock": 2,
        "base_vol_percent": 100,
        "recent_growth": 1.0,
        "buy_power": -1.0,
        "each_person_buy": 1,
        "free_float_share": 38,
        "order_value": 59,
        "ath_diff": null,
        "expected_days": 27982.0,
        "buy_to_failure": 0
    },
    {
        "name": "ناما",
        "queue_order_count": 382,
        "total_queue_value": 37.7,
        "solid": true,
        "growth": 1.35,
        "demand_ratio": 9.6,
        "vol_ratio": 3.27,
        "market": 1.9,
        "group": "خودرو و ساخت قطعات",
        "pe_ttm": 7.2,
        "chance": 0.22,
        "days_lock": 8,
        "base_vol_percent": 100,
        "recent_growth": 1.3,
        "buy_power": 4.7,
        "each_person_buy": 175,
        "free_float_share": 10,
        "order_value": 148,
        "ath_diff": null,
        "expected_days": 2.9,
        "buy_to_failure": 35
    },
    {
        "name": "دفارا3",
        "queue_order_count": 378,
        "total_queue_value": 41.1,
        "solid": true,
        "growth": 1.2,
        "demand_ratio": 1358.4,
        "vol_ratio": 1.11,
        "market": 10.3,
        "group": "مواد و محصولات دارویی",
        "pe_ttm": 6.9,
        "chance": 0.15,
        "days_lock": 3,
        "base_vol_percent": 100,
        "recent_growth": 1.24,
        "buy_power": -1.0,
        "each_person_buy": 33,
        "free_float_share": 33,
        "order_value": 111,
        "ath_diff": null,
        "expected_days": 1223.8,
        "buy_to_failure": 628
    },
    {
        "name": "شفن",
        "queue_order_count": 374,
        "total_queue_value": 37.8,
        "solid": true,
        "growth": 1.23,
        "demand_ratio": 12.6,
        "vol_ratio": 4.54,
        "market": 14.7,
        "group": "محصولات شیمیایی",
        "pe_ttm": 13.3,
        "chance": 0.1,
        "days_lock": 6,
        "base_vol_percent": 100,
        "recent_growth": 1.16,
        "buy_power": 3.8,
        "each_person_buy": 163,
        "free_float_share": 14,
        "order_value": 190,
        "ath_diff": null,
        "expected_days": 2.8,
        "buy_to_failure": 21
    },
    {
        "name": "ددانا",
        "queue_order_count": 362,
        "total_queue_value": 44.9,
        "solid": true,
        "growth": 1.58,
        "demand_ratio": 8.6,
        "vol_ratio": 3.87,
        "market": 12.1,
        "group": "مواد و محصولات دارویی",
        "pe_ttm": 6.1,
        "chance": 0.09,
        "days_lock": 17,
        "base_vol_percent": 100,
        "recent_growth": 1.63,
        "buy_power": 20.4,
        "each_person_buy": 173,
        "free_float_share": 10,
        "order_value": 168,
        "ath_diff": null,
        "expected_days": 2.2,
        "buy_to_failure": 16
    },
    {
        "name": "دتوزیع",
        "queue_order_count": 360,
        "total_queue_value": 31.3,
        "solid": true,
        "growth": 2.87,
        "demand_ratio": 3.6,
        "vol_ratio": 0.5,
        "market": 11.9,
        "group": "مواد و محصولات دارویی",
        "pe_ttm": 7.6,
        "chance": 0.05,
        "days_lock": 22,
        "base_vol_percent": 100,
        "recent_growth": 1.77,
        "buy_power": 5.1,
        "each_person_buy": 160,
        "free_float_share": 13,
        "order_value": 158,
        "ath_diff": null,
        "expected_days": 7.2,
        "buy_to_failure": 10
    },
    {
        "name": "زفجر",
        "queue_order_count": 343,
        "total_queue_value": 48.9,
        "solid": true,
        "growth": 3.0,
        "demand_ratio": 6.4,
        "vol_ratio": 0.58,
        "market": 3.6,
        "group": "زراعت و خدمات وابسته",
        "pe_ttm": 5.9,
        "chance": 0.06,
        "days_lock": 23,
        "base_vol_percent": 100,
        "recent_growth": 1.83,
        "buy_power": 33.7,
        "each_person_buy": 191,
        "free_float_share": 19,
        "order_value": 398,
        "ath_diff": null,
        "expected_days": 11.0,
        "buy_to_failure": 32
    },
    {
        "name": "انرژی",
        "queue_order_count": 329,
        "total_queue_value": 46.4,
        "solid": false,
        "growth": 2.17,
        "demand_ratio": 1.2,
        "vol_ratio": 3.46,
        "market": 7.0,
        "group": "فعالیتهای کمکی به نهادهای مالی واسط",
        "pe_ttm": 41.5,
        "chance": 10.64,
        "days_lock": 23,
        "base_vol_percent": 100,
        "recent_growth": 1.91,
        "buy_power": 1.4,
        "each_person_buy": 153,
        "free_float_share": 79,
        "order_value": 173,
        "ath_diff": null,
        "expected_days": 0.3,
        "buy_to_failure": 0
    },
    {
        "name": "شساخت",
        "queue_order_count": 318,
        "total_queue_value": 33.7,
        "solid": true,
        "growth": 2.63,
        "demand_ratio": 9.3,
        "vol_ratio": 1.06,
        "market": 12.6,
        "group": "استخراج نفت گاز و خدمات جنبی جز اکتشاف",
        "pe_ttm": 1.9,
        "chance": 0.03,
        "days_lock": 10,
        "base_vol_percent": 100,
        "recent_growth": 1.73,
        "buy_power": 18.1,
        "each_person_buy": 130,
        "free_float_share": 5,
        "order_value": 167,
        "ath_diff": null,
        "expected_days": 8.8,
        "buy_to_failure": 6
    },
    {
        "name": "فتوسا",
        "queue_order_count": 309,
        "total_queue_value": 21.4,
        "solid": true,
        "growth": 1.4,
        "demand_ratio": 5.9,
        "vol_ratio": 4.33,
        "market": 1.0,
        "group": "فلزات اساسی",
        "pe_ttm": 3.1,
        "chance": 0.12,
        "days_lock": 3,
        "base_vol_percent": 100,
        "recent_growth": 1.55,
        "buy_power": 70.3,
        "each_person_buy": 133,
        "free_float_share": 30,
        "order_value": 145,
        "ath_diff": null,
        "expected_days": 1.4,
        "buy_to_failure": 18
    },
    {
        "name": "وگردش",
        "queue_order_count": 306,
        "total_queue_value": 21.4,
        "solid": false,
        "growth": 3.16,
        "demand_ratio": 0.5,
        "vol_ratio": 1.44,
        "market": 20.1,
        "group": "بانکها و موسسات اعتباری",
        "pe_ttm": 1.3,
        "chance": 51.45,
        "days_lock": 1,
        "base_vol_percent": 100,
        "recent_growth": 1.66,
        "buy_power": 2.1,
        "each_person_buy": 185,
        "free_float_share": 28,
        "order_value": 50,
        "ath_diff": null,
        "expected_days": 0.3,
        "buy_to_failure": 0
    },
    {
        "name": "وساپا",
        "queue_order_count": 297,
        "total_queue_value": 29.6,
        "solid": false,
        "growth": 1.98,
        "demand_ratio": 0.2,
        "vol_ratio": 1.62,
        "market": 18.3,
        "group": "سرمایه گذاریها",
        "pe_ttm": 2.4,
        "chance": 62.2,
        "days_lock": 1,
        "base_vol_percent": 100,
        "recent_growth": 1.11,
        "buy_power": 1.5,
        "each_person_buy": 212,
        "free_float_share": 33,
        "order_value": 140,
        "ath_diff": null,
        "expected_days": 0.1,
        "buy_to_failure": 0
    },
    {
        "name": "خگستر3",
        "queue_order_count": 294,
        "total_queue_value": 29.4,
        "solid": true,
        "growth": 1.2,
        "demand_ratio": 1.6,
        "vol_ratio": 0.01,
        "market": 19.2,
        "group": "خودرو و ساخت قطعات",
        "pe_ttm": 36.3,
        "chance": 0.09,
        "days_lock": 9,
        "base_vol_percent": 100,
        "recent_growth": 1.19,
        "buy_power": -1.0,
        "each_person_buy": 44,
        "free_float_share": 49,
        "order_value": 130,
        "ath_diff": null,
        "expected_days": 160.0,
        "buy_to_failure": 68
    },
    {
        "name": "دقاضی",
        "queue_order_count": 290,
        "total_queue_value": 43.7,
        "solid": true,
        "growth": 2.6,
        "demand_ratio": 9.7,
        "vol_ratio": 0.41,
        "market": 15.1,
        "group": "مواد و محصولات دارویی",
        "pe_ttm": 9.5,
        "chance": 0.01,
        "days_lock": 22,
        "base_vol_percent": 100,
        "recent_growth": 1.9,
        "buy_power": 24.2,
        "each_person_buy": 229,
        "free_float_share": 11,
        "order_value": 145,
        "ath_diff": null,
        "expected_days": 23.7,
        "buy_to_failure": 2
    },
    {
        "name": "فگستر",
        "queue_order_count": 286,
        "total_queue_value": 27.4,
        "solid": true,
        "growth": 1.7,
        "demand_ratio": 3.9,
        "vol_ratio": 0.14,
        "market": 1.5,
        "group": "فلزات اساسی",
        "pe_ttm": 3.8,
        "chance": 0.01,
        "days_lock": 19,
        "base_vol_percent": 100,
        "recent_growth": 1.75,
        "buy_power": 28.2,
        "each_person_buy": 158,
        "free_float_share": 30,
        "order_value": 174,
        "ath_diff": null,
        "expected_days": 27.9,
        "buy_to_failure": 3
    },
    {
        "name": "دزهراوی",
        "queue_order_count": 236,
        "total_queue_value": 14.8,
        "solid": true,
        "growth": 2.01,
        "demand_ratio": 3.6,
        "vol_ratio": 1.61,
        "market": 2.5,
        "group": "مواد و محصولات دارویی",
        "pe_ttm": 7.9,
        "chance": 0.42,
        "days_lock": 22,
        "base_vol_percent": 100,
        "recent_growth": 1.7,
        "buy_power": 13.4,
        "each_person_buy": 220,
        "free_float_share": 21,
        "order_value": 95,
        "ath_diff": null,
        "expected_days": 2.2,
        "buy_to_failure": 43
    },
    {
        "name": "انرژی3",
        "queue_order_count": 236,
        "total_queue_value": 38.4,
        "solid": true,
        "growth": 1.28,
        "demand_ratio": 1163.7,
        "vol_ratio": 1.63,
        "market": 7.0,
        "group": "فعالیتهای کمکی به نهادهای مالی واسط",
        "pe_ttm": 41.5,
        "chance": 0.02,
        "days_lock": 3,
        "base_vol_percent": 100,
        "recent_growth": 1.31,
        "buy_power": -1.0,
        "each_person_buy": 54,
        "free_float_share": 79,
        "order_value": 173,
        "ath_diff": null,
        "expected_days": 713.9,
        "buy_to_failure": 78
    },
    {
        "name": "شبندر",
        "queue_order_count": 231,
        "total_queue_value": 18.8,
        "solid": false,
        "growth": 2.58,
        "demand_ratio": 0.0,
        "vol_ratio": 3.02,
        "market": 488.0,
        "group": "فراورده های نفتی، کک و سوخت هسته ای",
        "pe_ttm": 5.6,
        "chance": 4200.61,
        "days_lock": 1,
        "base_vol_percent": 100,
        "recent_growth": 1.66,
        "buy_power": -1.7,
        "each_person_buy": 118,
        "free_float_share": 30,
        "order_value": 119,
        "ath_diff": null,
        "expected_days": 0.0,
        "buy_to_failure": 0
    },
    {
        "name": "سپید",
        "queue_order_count": 223,
        "total_queue_value": 30.5,
        "solid": false,
        "growth": 5.4,
        "demand_ratio": 0.5,
        "vol_ratio": 4.49,
        "market": 24.8,
        "group": "زراعت و خدمات وابسته",
        "pe_ttm": 5.9,
        "chance": 33.19,
        "days_lock": 1,
        "base_vol_percent": 100,
        "recent_growth": 1.97,
        "buy_power": -1.1,
        "each_person_buy": 191,
        "free_float_share": 18,
        "order_value": 275,
        "ath_diff": null,
        "expected_days": 0.1,
        "buy_to_failure": 0
    },
    {
        "name": "غدانه",
        "queue_order_count": 218,
        "total_queue_value": 19.2,
        "solid": true,
        "growth": 1.72,
        "demand_ratio": 0.9,
        "vol_ratio": 0.27,
        "market": 2.0,
        "group": "محصولات غذایی و آشامیدنی به جز قند و شکر",
        "pe_ttm": 6.5,
        "chance": 0.11,
        "days_lock": 20,
        "base_vol_percent": 100,
        "recent_growth": 1.77,
        "buy_power": 3.4,
        "each_person_buy": 182,
        "free_float_share": 31,
        "order_value": 100,
        "ath_diff": null,
        "expected_days": 3.3,
        "buy_to_failure": 12
    },
    {
        "name": "شراز",
        "queue_order_count": 214,
        "total_queue_value": 35.4,
        "solid": false,
        "growth": 3.29,
        "demand_ratio": 1.4,
        "vol_ratio": 5.69,
        "market": 60.9,
        "group": "فراورده های نفتی، کک و سوخت هسته ای",
        "pe_ttm": 8.0,
        "chance": 1.13,
        "days_lock": 20,
        "base_vol_percent": 100,
        "recent_growth": 1.78,
        "buy_power": -1.1,
        "each_person_buy": 205,
        "free_float_share": 24,
        "order_value": 553,
        "ath_diff": null,
        "expected_days": 0.2,
        "buy_to_failure": 0
    },
    {
        "name": "ولملت",
        "queue_order_count": 206,
        "total_queue_value": 26.8,
        "solid": true,
        "growth": 3.18,
        "demand_ratio": 3.3,
        "vol_ratio": 0.28,
        "market": 2.2,
        "group": "سایر واسطه گریهای مالی",
        "pe_ttm": 22.5,
        "chance": 0.05,
        "days_lock": 39,
        "base_vol_percent": 100,
        "recent_growth": 2.01,
        "buy_power": 3.3,
        "each_person_buy": 132,
        "free_float_share": 16,
        "order_value": 144,
        "ath_diff": null,
        "expected_days": 11.8,
        "buy_to_failure": 10
    },
    {
        "name": "تیپیکو3",
        "queue_order_count": 192,
        "total_queue_value": 90.0,
        "solid": false,
        "growth": 1.0,
        "demand_ratio": 3148.1,
        "vol_ratio": 0.0,
        "market": 68.2,
        "group": "مواد و محصولات دارویی",
        "pe_ttm": 14.7,
        "chance": 0.0,
        "days_lock": 1,
        "base_vol_percent": 100,
        "recent_growth": 1.03,
        "buy_power": 0,
        "each_person_buy": 0,
        "free_float_share": 18,
        "order_value": 619,
        "ath_diff": null,
        "expected_days": 1,
        "buy_to_failure": 0
    },
    {
        "name": "ساروم",
        "queue_order_count": 186,
        "total_queue_value": 40.8,
        "solid": false,
        "growth": 1.75,
        "demand_ratio": 0.7,
        "vol_ratio": 4.14,
        "market": 17.7,
        "group": "سیمان، آهک و گچ",
        "pe_ttm": 6.0,
        "chance": 4.67,
        "days_lock": 18,
        "base_vol_percent": 100,
        "recent_growth": 1.39,
        "buy_power": -2.4,
        "each_person_buy": 82,
        "free_float_share": 25,
        "order_value": 884,
        "ath_diff": null,
        "expected_days": 0.2,
        "buy_to_failure": 0
    },
    {
        "name": "پترول",
        "queue_order_count": 183,
        "total_queue_value": 4.0,
        "solid": false,
        "growth": 1.45,
        "demand_ratio": 0.2,
        "vol_ratio": 2.94,
        "market": 18.3,
        "group": "محصولات شیمیایی",
        "pe_ttm": 9.0,
        "chance": 4.33,
        "days_lock": 5,
        "base_vol_percent": 100,
        "recent_growth": 1.3,
        "buy_power": -1.1,
        "each_person_buy": 71,
        "free_float_share": 22,
        "order_value": 73,
        "ath_diff": null,
        "expected_days": 0.1,
        "buy_to_failure": 0
    },
    {
        "name": "وپاسار",
        "queue_order_count": 183,
        "total_queue_value": 17.3,
        "solid": false,
        "growth": 3.2,
        "demand_ratio": 0.3,
        "vol_ratio": 1.55,
        "market": 485.0,
        "group": "بانکها و موسسات اعتباری",
        "pe_ttm": 12.7,
        "chance": 10.68,
        "days_lock": 10,
        "base_vol_percent": 100,
        "recent_growth": 1.84,
        "buy_power": 1.2,
        "each_person_buy": 153,
        "free_float_share": 24,
        "order_value": 103,
        "ath_diff": null,
        "expected_days": 0.2,
        "buy_to_failure": 0
    },
    {
        "name": "تاپیکو",
        "queue_order_count": 179,
        "total_queue_value": 36.0,
        "solid": false,
        "growth": 1.93,
        "demand_ratio": 0.2,
        "vol_ratio": 5.7,
        "market": 269.4,
        "group": "محصولات شیمیایی",
        "pe_ttm": 12.7,
        "chance": 42.5,
        "days_lock": 1,
        "base_vol_percent": 100,
        "recent_growth": 1.36,
        "buy_power": -1.4,
        "each_person_buy": 219,
        "free_float_share": 11,
        "order_value": 265,
        "ath_diff": null,
        "expected_days": 0.0,
        "buy_to_failure": 0
    },
    {
        "name": "وپاسار3",
        "queue_order_count": 178,
        "total_queue_value": 32.6,
        "solid": true,
        "growth": 1.03,
        "demand_ratio": 25808.1,
        "vol_ratio": 0.41,
        "market": 484.5,
        "group": "بانکها و موسسات اعتباری",
        "pe_ttm": 12.7,
        "chance": 0.0,
        "days_lock": 2,
        "base_vol_percent": 100,
        "recent_growth": 1.05,
        "buy_power": -1.0,
        "each_person_buy": 1,
        "free_float_share": 24,
        "order_value": 103,
        "ath_diff": null,
        "expected_days": 62946.6,
        "buy_to_failure": 0
    },
    {
        "name": "دحاوی",
        "queue_order_count": 177,
        "total_queue_value": 16.1,
        "solid": true,
        "growth": 2.49,
        "demand_ratio": 14.5,
        "vol_ratio": 0.63,
        "market": 1.7,
        "group": "مواد و محصولات دارویی",
        "pe_ttm": 5.2,
        "chance": 0.01,
        "days_lock": 16,
        "base_vol_percent": 37,
        "recent_growth": 1.38,
        "buy_power": 1.7,
        "each_person_buy": 87,
        "free_float_share": 24,
        "order_value": 107,
        "ath_diff": null,
        "expected_days": 23.0,
        "buy_to_failure": 2
    },
    {
        "name": "دلقما",
        "queue_order_count": 173,
        "total_queue_value": 10.4,
        "solid": false,
        "growth": 2.32,
        "demand_ratio": 0.8,
        "vol_ratio": 2.66,
        "market": 3.9,
        "group": "مواد و محصولات دارویی",
        "pe_ttm": 6.1,
        "chance": 10.03,
        "days_lock": 21,
        "base_vol_percent": 100,
        "recent_growth": 1.79,
        "buy_power": 1.7,
        "each_person_buy": 176,
        "free_float_share": 27,
        "order_value": 151,
        "ath_diff": null,
        "expected_days": 0.3,
        "buy_to_failure": 0
    },
    {
        "name": "شسپا",
        "queue_order_count": 169,
        "total_queue_value": 12.1,
        "solid": false,
        "growth": 3.37,
        "demand_ratio": 0.2,
        "vol_ratio": 4.98,
        "market": 85.1,
        "group": "فراورده های نفتی، کک و سوخت هسته ای",
        "pe_ttm": 5.0,
        "chance": 11.78,
        "days_lock": 22,
        "base_vol_percent": 100,
        "recent_growth": 1.88,
        "buy_power": -1.4,
        "each_person_buy": 117,
        "free_float_share": 15,
        "order_value": 152,
        "ath_diff": null,
        "expected_days": 0.0,
        "buy_to_failure": 0
    },
    {
        "name": "کوچین",
        "queue_order_count": 167,
        "total_queue_value": 14.9,
        "solid": false,
        "growth": 1.68,
        "demand_ratio": 0.6,
        "vol_ratio": 6.79,
        "market": 9.3,
        "group": "محصولات غذایی و آشامیدنی به جز قند و شکر",
        "pe_ttm": 7.7,
        "chance": 4.18,
        "days_lock": 19,
        "base_vol_percent": 100,
        "recent_growth": 1.71,
        "buy_power": 2.1,
        "each_person_buy": 105,
        "free_float_share": 15,
        "order_value": 117,
        "ath_diff": null,
        "expected_days": 0.1,
        "buy_to_failure": 0
    },
    {
        "name": "بتهران",
        "queue_order_count": 163,
        "total_queue_value": 22.8,
        "solid": true,
        "growth": 1.95,
        "demand_ratio": 6.9,
        "vol_ratio": 0.39,
        "market": 2.4,
        "group": "بیمه وصندوق بازنشستگی به جزتامین اجتماعی",
        "pe_ttm": 4.6,
        "chance": 0.03,
        "days_lock": 22,
        "base_vol_percent": 100,
        "recent_growth": 1.89,
        "buy_power": -1.8,
        "each_person_buy": 129,
        "free_float_share": 18,
        "order_value": 151,
        "ath_diff": null,
        "expected_days": 17.7,
        "buy_to_failure": 7
    },
    {
        "name": "کچادح",
        "queue_order_count": 163,
        "total_queue_value": 4.1,
        "solid": false,
        "growth": 1.19,
        "demand_ratio": 3.8,
        "vol_ratio": 22.0,
        "market": 5.8,
        "group": "استخراج کانه های فلزی",
        "pe_ttm": 8.8,
        "chance": 1997.03,
        "days_lock": 2,
        "base_vol_percent": 100,
        "recent_growth": 1.15,
        "buy_power": 9.8,
        "each_person_buy": 41,
        "free_float_share": 29,
        "order_value": 41,
        "ath_diff": null,
        "expected_days": 0.2,
        "buy_to_failure": 0
    },
    {
        "name": "فارس",
        "queue_order_count": 159,
        "total_queue_value": 14.4,
        "solid": false,
        "growth": 2.03,
        "demand_ratio": 0.1,
        "vol_ratio": 6.33,
        "market": 1282.0,
        "group": "محصولات شیمیایی",
        "pe_ttm": 6.7,
        "chance": 17.29,
        "days_lock": 4,
        "base_vol_percent": 100,
        "recent_growth": 1.23,
        "buy_power": 1.7,
        "each_person_buy": 310,
        "free_float_share": 33,
        "order_value": 128,
        "ath_diff": null,
        "expected_days": 0.0,
        "buy_to_failure": 0
    },
    {
        "name": "حسینا",
        "queue_order_count": 159,
        "total_queue_value": 13.1,
        "solid": false,
        "growth": 2.16,
        "demand_ratio": 0.2,
        "vol_ratio": 2.28,
        "market": 15.8,
        "group": "حمل ونقل، انبارداری و ارتباطات",
        "pe_ttm": 6.8,
        "chance": 3.23,
        "days_lock": 13,
        "base_vol_percent": 100,
        "recent_growth": 1.37,
        "buy_power": -1.3,
        "each_person_buy": 125,
        "free_float_share": 16,
        "order_value": 175,
        "ath_diff": null,
        "expected_days": 0.1,
        "buy_to_failure": 0
    },
    {
        "name": "سباقر3",
        "queue_order_count": 158,
        "total_queue_value": 40.5,
        "solid": true,
        "growth": 1.05,
        "demand_ratio": 1307.0,
        "vol_ratio": 2.39,
        "market": 12.9,
        "group": "سیمان، آهک و گچ",
        "pe_ttm": 6.6,
        "chance": 0.22,
        "days_lock": 3,
        "base_vol_percent": 100,
        "recent_growth": 1.09,
        "buy_power": -1.0,
        "each_person_buy": 74,
        "free_float_share": 58,
        "order_value": 1071,
        "ath_diff": null,
        "expected_days": 546.9,
        "buy_to_failure": 4101
    },
    {
        "name": "شراز3",
        "queue_order_count": 153,
        "total_queue_value": 59.0,
        "solid": true,
        "growth": 1.23,
        "demand_ratio": 24.4,
        "vol_ratio": 0.01,
        "market": 60.9,
        "group": "فراورده های نفتی، کک و سوخت هسته ای",
        "pe_ttm": 8.0,
        "chance": 0.04,
        "days_lock": 2,
        "base_vol_percent": 100,
        "recent_growth": 1.26,
        "buy_power": -1.0,
        "each_person_buy": 24,
        "free_float_share": 24,
        "order_value": 553,
        "ath_diff": null,
        "expected_days": 2440.0,
        "buy_to_failure": 1641
    },
    {
        "name": "شسپا3",
        "queue_order_count": 148,
        "total_queue_value": 13.2,
        "solid": false,
        "growth": 1.28,
        "demand_ratio": 159.8,
        "vol_ratio": 0.0,
        "market": 84.1,
        "group": "فراورده های نفتی، کک و سوخت هسته ای",
        "pe_ttm": 5.0,
        "chance": 0.0,
        "days_lock": 2,
        "base_vol_percent": 100,
        "recent_growth": 1.3,
        "buy_power": 0,
        "each_person_buy": 0,
        "free_float_share": 15,
        "order_value": 150,
        "ath_diff": null,
        "expected_days": 1,
        "buy_to_failure": 0
    },
    {
        "name": "وگردش3",
        "queue_order_count": 142,
        "total_queue_value": 12.5,
        "solid": true,
        "growth": 1.24,
        "demand_ratio": 46.7,
        "vol_ratio": 0.38,
        "market": 20.0,
        "group": "بانکها و موسسات اعتباری",
        "pe_ttm": 1.3,
        "chance": 0.2,
        "days_lock": 7,
        "base_vol_percent": 100,
        "recent_growth": 1.21,
        "buy_power": -1.0,
        "each_person_buy": 100,
        "free_float_share": 28,
        "order_value": 50,
        "ath_diff": null,
        "expected_days": 122.9,
        "buy_to_failure": 47
    },
    {
        "name": "پترول3",
        "queue_order_count": 142,
        "total_queue_value": 8.7,
        "solid": false,
        "growth": 1.12,
        "demand_ratio": 322.1,
        "vol_ratio": 0.0,
        "market": 18.2,
        "group": "محصولات شیمیایی",
        "pe_ttm": 9.0,
        "chance": 0.0,
        "days_lock": 2,
        "base_vol_percent": 100,
        "recent_growth": 1.26,
        "buy_power": 0,
        "each_person_buy": 0,
        "free_float_share": 22,
        "order_value": 72,
        "ath_diff": null,
        "expected_days": 1,
        "buy_to_failure": 0
    },
    {
        "name": "وخاور3",
        "queue_order_count": 141,
        "total_queue_value": 26.0,
        "solid": false,
        "growth": 1.28,
        "demand_ratio": 144595.1,
        "vol_ratio": 0.0,
        "market": 57.5,
        "group": "بانکها و موسسات اعتباری",
        "pe_ttm": 4.0,
        "chance": 0.0,
        "days_lock": 2,
        "base_vol_percent": 100,
        "recent_growth": 1.05,
        "buy_power": 0,
        "each_person_buy": 0,
        "free_float_share": 70,
        "order_value": 191,
        "ath_diff": null,
        "expected_days": 1,
        "buy_to_failure": 0
    },
    {
        "name": "سیتا3",
        "queue_order_count": 140,
        "total_queue_value": 34.9,
        "solid": true,
        "growth": 1.0,
        "demand_ratio": 2940.5,
        "vol_ratio": 1.02,
        "market": 64.9,
        "group": "سیمان، آهک و گچ",
        "pe_ttm": 13.0,
        "chance": 0.02,
        "days_lock": 2,
        "base_vol_percent": 100,
        "recent_growth": 1.0,
        "buy_power": 4.0,
        "each_person_buy": 12,
        "free_float_share": 10,
        "order_value": 295,
        "ath_diff": null,
        "expected_days": 2882.8,
        "buy_to_failure": 516
    },
    {
        "name": "هرمز3",
        "queue_order_count": 136,
        "total_queue_value": 27.1,
        "solid": true,
        "growth": 1.0,
        "demand_ratio": 32670.3,
        "vol_ratio": 12.47,
        "market": 37.9,
        "group": "فلزات اساسی",
        "pe_ttm": 16.7,
        "chance": 0.02,
        "days_lock": 2,
        "base_vol_percent": 100,
        "recent_growth": 1.17,
        "buy_power": 2.0,
        "each_person_buy": 10,
        "free_float_share": 11,
        "order_value": 108,
        "ath_diff": null,
        "expected_days": 2619.9,
        "buy_to_failure": 172
    },
    {
        "name": "فایرا3",
        "queue_order_count": 130,
        "total_queue_value": 21.5,
        "solid": true,
        "growth": 1.09,
        "demand_ratio": 24832.3,
        "vol_ratio": 5.9,
        "market": 63.3,
        "group": "فلزات اساسی",
        "pe_ttm": 7.7,
        "chance": 0.0,
        "days_lock": 3,
        "base_vol_percent": 100,
        "recent_growth": 1.12,
        "buy_power": -1.0,
        "each_person_buy": 5,
        "free_float_share": 50,
        "order_value": 102,
        "ath_diff": null,
        "expected_days": 4208.9,
        "buy_to_failure": 0
    },
    {
        "name": "حسینا3",
        "queue_order_count": 130,
        "total_queue_value": 17.5,
        "solid": true,
        "growth": 1.03,
        "demand_ratio": 731.9,
        "vol_ratio": 2.26,
        "market": 15.8,
        "group": "حمل ونقل، انبارداری و ارتباطات",
        "pe_ttm": 6.8,
        "chance": 0.15,
        "days_lock": 2,
        "base_vol_percent": 100,
        "recent_growth": 1.06,
        "buy_power": 2.0,
        "each_person_buy": 54,
        "free_float_share": 16,
        "order_value": 175,
        "ath_diff": null,
        "expected_days": 323.8,
        "buy_to_failure": 281
    },
    {
        "name": "فمراد",
        "queue_order_count": 127,
        "total_queue_value": 3.9,
        "solid": true,
        "growth": 1.09,
        "demand_ratio": 23.3,
        "vol_ratio": 0.61,
        "market": 0.5,
        "group": "فلزات اساسی",
        "pe_ttm": -33.7,
        "chance": 0.01,
        "days_lock": 6,
        "base_vol_percent": 100,
        "recent_growth": 0.26,
        "buy_power": 32.0,
        "each_person_buy": 51,
        "free_float_share": 42,
        "order_value": 94,
        "ath_diff": null,
        "expected_days": 38.2,
        "buy_to_failure": 2
    },
    {
        "name": "سپید3",
        "queue_order_count": 127,
        "total_queue_value": 24.6,
        "solid": true,
        "growth": 1.03,
        "demand_ratio": 3320.4,
        "vol_ratio": 0.36,
        "market": 24.7,
        "group": "زراعت و خدمات وابسته",
        "pe_ttm": 5.9,
        "chance": 0.0,
        "days_lock": 2,
        "base_vol_percent": 100,
        "recent_growth": 1.24,
        "buy_power": 3.0,
        "each_person_buy": 3,
        "free_float_share": 18,
        "order_value": 274,
        "ath_diff": null,
        "expected_days": 9223.3,
        "buy_to_failure": 0
    },
    {
        "name": "وایرا",
        "queue_order_count": 125,
        "total_queue_value": 7.1,
        "solid": true,
        "growth": 1.08,
        "demand_ratio": 52.3,
        "vol_ratio": 3.8,
        "market": 0.5,
        "group": "سرمایه گذاریها",
        "pe_ttm": 13.4,
        "chance": 0.02,
        "days_lock": 4,
        "base_vol_percent": 100,
        "recent_growth": 1.02,
        "buy_power": 5.2,
        "each_person_buy": 74,
        "free_float_share": 21,
        "order_value": 89,
        "ath_diff": null,
        "expected_days": 13.8,
        "buy_to_failure": 3
    },
    {
        "name": "غبهار",
        "queue_order_count": 123,
        "total_queue_value": 19.0,
        "solid": true,
        "growth": 1.24,
        "demand_ratio": 93.0,
        "vol_ratio": 3.16,
        "market": 0.6,
        "group": "محصولات غذایی و آشامیدنی به جز قند و شکر",
        "pe_ttm": 4.3,
        "chance": 0.01,
        "days_lock": 9,
        "base_vol_percent": 44,
        "recent_growth": 1.28,
        "buy_power": 4.3,
        "each_person_buy": 215,
        "free_float_share": 24,
        "order_value": 101,
        "ath_diff": null,
        "expected_days": 29.4,
        "buy_to_failure": 2
    },
    {
        "name": "پاریز3",
        "queue_order_count": 117,
        "total_queue_value": 3.1,
        "solid": true,
        "growth": 1.0,
        "demand_ratio": 101.6,
        "vol_ratio": 22.0,
        "market": 6.7,
        "group": "انبوه سازی، املاک و مستغلات",
        "pe_ttm": 40.7,
        "chance": 0.67,
        "days_lock": 1,
        "base_vol_percent": 100,
        "recent_growth": 1.03,
        "buy_power": 70.4,
        "each_person_buy": 45,
        "free_float_share": 13,
        "order_value": 335,
        "ath_diff": null,
        "expected_days": 4.6,
        "buy_to_failure": 255
    },
    {
        "name": "دروز",
        "queue_order_count": 116,
        "total_queue_value": 9.3,
        "solid": true,
        "growth": 1.1,
        "demand_ratio": 665.9,
        "vol_ratio": 3.33,
        "market": 1.3,
        "group": "مواد و محصولات دارویی",
        "pe_ttm": 87.8,
        "chance": 0.0,
        "days_lock": 3,
        "base_vol_percent": 100,
        "recent_growth": 1.09,
        "buy_power": 8.0,
        "each_person_buy": 47,
        "free_float_share": 14,
        "order_value": 184,
        "ath_diff": null,
        "expected_days": 200.0,
        "buy_to_failure": 0
    },
    {
        "name": "وپارس3",
        "queue_order_count": 111,
        "total_queue_value": 6.8,
        "solid": true,
        "growth": 1.15,
        "demand_ratio": 324.3,
        "vol_ratio": 0.09,
        "market": 59.0,
        "group": "بانکها و موسسات اعتباری",
        "pe_ttm": 1.3,
        "chance": 0.0,
        "days_lock": 7,
        "base_vol_percent": 100,
        "recent_growth": 1.18,
        "buy_power": -1.0,
        "each_person_buy": 2,
        "free_float_share": 20,
        "order_value": 75,
        "ath_diff": null,
        "expected_days": 3603.3,
        "buy_to_failure": 0
    },
    {
        "name": "فزرین",
        "queue_order_count": 111,
        "total_queue_value": 8.4,
        "solid": true,
        "growth": 2.14,
        "demand_ratio": 2.3,
        "vol_ratio": 1.71,
        "market": 2.0,
        "group": "فلزات اساسی",
        "pe_ttm": 5.0,
        "chance": 0.24,
        "days_lock": 7,
        "base_vol_percent": 100,
        "recent_growth": 1.77,
        "buy_power": 5.4,
        "each_person_buy": 195,
        "free_float_share": 37,
        "order_value": 184,
        "ath_diff": null,
        "expected_days": 1.3,
        "buy_to_failure": 46
    },
    {
        "name": "فرابورس",
        "queue_order_count": 107,
        "total_queue_value": 10.4,
        "solid": false,
        "growth": 1.88,
        "demand_ratio": 0.2,
        "vol_ratio": 2.72,
        "market": 9.7,
        "group": "فعالیتهای کمکی به نهادهای مالی واسط",
        "pe_ttm": 18.2,
        "chance": 13.2,
        "days_lock": 1,
        "base_vol_percent": 100,
        "recent_growth": 1.72,
        "buy_power": 2.1,
        "each_person_buy": 222,
        "free_float_share": 52,
        "order_value": 122,
        "ath_diff": null,
        "expected_days": 0.1,
        "buy_to_failure": 0
    },
    {
        "name": "غمینو",
        "queue_order_count": 106,
        "total_queue_value": 8.8,
        "solid": false,
        "growth": 2.17,
        "demand_ratio": 0.6,
        "vol_ratio": 3.35,
        "market": 3.8,
        "group": "محصولات غذایی و آشامیدنی به جز قند و شکر",
        "pe_ttm": 6.5,
        "chance": 7.49,
        "days_lock": 19,
        "base_vol_percent": 100,
        "recent_growth": 1.59,
        "buy_power": -1.4,
        "each_person_buy": 99,
        "free_float_share": 31,
        "order_value": 109,
        "ath_diff": null,
        "expected_days": 0.2,
        "buy_to_failure": 0
    },
    {
        "name": "ورنا3",
        "queue_order_count": 101,
        "total_queue_value": 5.5,
        "solid": true,
        "growth": 1.09,
        "demand_ratio": 0.7,
        "vol_ratio": 0.02,
        "market": 13.8,
        "group": "خودرو و ساخت قطعات",
        "pe_ttm": 23.7,
        "chance": 0.92,
        "days_lock": 10,
        "base_vol_percent": 100,
        "recent_growth": 1.06,
        "buy_power": -2.0,
        "each_person_buy": 47,
        "free_float_share": 32,
        "order_value": 110,
        "ath_diff": null,
        "expected_days": 35.0,
        "buy_to_failure": 0
    },
    {
        "name": "وساپا3",
        "queue_order_count": 99,
        "total_queue_value": 8.8,
        "solid": true,
        "growth": 1.21,
        "demand_ratio": 2.7,
        "vol_ratio": 0.0,
        "market": 18.2,
        "group": "سرمایه گذاریها",
        "pe_ttm": 2.4,
        "chance": 0.0,
        "days_lock": 9,
        "base_vol_percent": 100,
        "recent_growth": 1.18,
        "buy_power": 2.0,
        "each_person_buy": 3,
        "free_float_share": 33,
        "order_value": 140,
        "ath_diff": null,
        "expected_days": 1,
        "buy_to_failure": 0
    },
    {
        "name": "بنیرو",
        "queue_order_count": 97,
        "total_queue_value": 6.8,
        "solid": true,
        "growth": 1.4,
        "demand_ratio": 1.0,
        "vol_ratio": 1.67,
        "market": 7.4,
        "group": "ماشین آلات و دستگاههای برقی",
        "pe_ttm": 3.4,
        "chance": 0.49,
        "days_lock": 8,
        "base_vol_percent": 100,
        "recent_growth": 1.45,
        "buy_power": 1.7,
        "each_person_buy": 148,
        "free_float_share": 35,
        "order_value": 124,
        "ath_diff": null,
        "expected_days": 0.6,
        "buy_to_failure": 62
    },
    {
        "name": "چکاوه",
        "queue_order_count": 96,
        "total_queue_value": 8.6,
        "solid": true,
        "growth": 1.36,
        "demand_ratio": 27.4,
        "vol_ratio": 10.92,
        "market": 0.5,
        "group": "محصولات کاغذی",
        "pe_ttm": -5.7,
        "chance": 0.18,
        "days_lock": 5,
        "base_vol_percent": 100,
        "recent_growth": 1.06,
        "buy_power": 1.3,
        "each_person_buy": 118,
        "free_float_share": 41,
        "order_value": 143,
        "ath_diff": null,
        "expected_days": 2.5,
        "buy_to_failure": 28
    },
    {
        "name": "تیپیکو",
        "queue_order_count": 94,
        "total_queue_value": 31.0,
        "solid": false,
        "growth": 3.0,
        "demand_ratio": 0.5,
        "vol_ratio": 4.22,
        "market": 70.2,
        "group": "مواد و محصولات دارویی",
        "pe_ttm": 15.2,
        "chance": 4.64,
        "days_lock": 23,
        "base_vol_percent": 100,
        "recent_growth": 1.8,
        "buy_power": -2.1,
        "each_person_buy": 174,
        "free_float_share": 18,
        "order_value": 638,
        "ath_diff": null,
        "expected_days": 0.1,
        "buy_to_failure": 0
    },
    {
        "name": "غپینو",
        "queue_order_count": 94,
        "total_queue_value": 5.4,
        "solid": false,
        "growth": 1.6,
        "demand_ratio": 0.2,
        "vol_ratio": 3.14,
        "market": 17.1,
        "group": "محصولات غذایی و آشامیدنی به جز قند و شکر",
        "pe_ttm": 8.0,
        "chance": 58.73,
        "days_lock": 1,
        "base_vol_percent": 100,
        "recent_growth": 1.54,
        "buy_power": -1.5,
        "each_person_buy": 53,
        "free_float_share": 38,
        "order_value": 62,
        "ath_diff": null,
        "expected_days": 0.1,
        "buy_to_failure": 0
    },
    {
        "name": "خکاوه",
        "queue_order_count": 92,
        "total_queue_value": 4.0,
        "solid": false,
        "growth": 1.31,
        "demand_ratio": 0.2,
        "vol_ratio": 1.07,
        "market": 3.5,
        "group": "خودرو و ساخت قطعات",
        "pe_ttm": 11.4,
        "chance": 6.4,
        "days_lock": 2,
        "base_vol_percent": 100,
        "recent_growth": 1.28,
        "buy_power": 1.3,
        "each_person_buy": 159,
        "free_float_share": 51,
        "order_value": 25,
        "ath_diff": null,
        "expected_days": 0.2,
        "buy_to_failure": 0
    },
    {
        "name": "غکورش3",
        "queue_order_count": 92,
        "total_queue_value": 6.2,
        "solid": false,
        "growth": 1.03,
        "demand_ratio": 25989.3,
        "vol_ratio": 0.0,
        "market": 73.9,
        "group": "محصولات غذایی و آشامیدنی به جز قند و شکر",
        "pe_ttm": 13.6,
        "chance": 0.0,
        "days_lock": 1,
        "base_vol_percent": 100,
        "recent_growth": 1.03,
        "buy_power": 0,
        "each_person_buy": 0,
        "free_float_share": 8,
        "order_value": 168,
        "ath_diff": null,
        "expected_days": 1,
        "buy_to_failure": 0
    },
    {
        "name": "زبینا",
        "queue_order_count": 91,
        "total_queue_value": 11.7,
        "solid": false,
        "growth": 3.44,
        "demand_ratio": 0.5,
        "vol_ratio": 2.31,
        "market": 4.3,
        "group": "زراعت و خدمات وابسته",
        "pe_ttm": 7.1,
        "chance": 14.86,
        "days_lock": 22,
        "base_vol_percent": 100,
        "recent_growth": 1.86,
        "buy_power": -1.6,
        "each_person_buy": 79,
        "free_float_share": 29,
        "order_value": 118,
        "ath_diff": null,
        "expected_days": 0.2,
        "buy_to_failure": 0
    },
    {
        "name": "بورس",
        "queue_order_count": 90,
        "total_queue_value": 10.1,
        "solid": false,
        "growth": 2.49,
        "demand_ratio": 0.2,
        "vol_ratio": 2.83,
        "market": 12.9,
        "group": "فعالیتهای کمکی به نهادهای مالی واسط",
        "pe_ttm": 19.1,
        "chance": 13.36,
        "days_lock": 1,
        "base_vol_percent": 100,
        "recent_growth": 1.89,
        "buy_power": 2.1,
        "each_person_buy": 228,
        "free_float_share": 47,
        "order_value": 107,
        "ath_diff": null,
        "expected_days": 0.1,
        "buy_to_failure": 0
    },
    {
        "name": "حپارسا",
        "queue_order_count": 90,
        "total_queue_value": 9.5,
        "solid": false,
        "growth": 2.94,
        "demand_ratio": 0.9,
        "vol_ratio": 3.12,
        "market": 2.6,
        "group": "حمل ونقل، انبارداری و ارتباطات",
        "pe_ttm": 7.0,
        "chance": 3.06,
        "days_lock": 20,
        "base_vol_percent": 100,
        "recent_growth": 1.76,
        "buy_power": -2.0,
        "each_person_buy": 92,
        "free_float_share": 23,
        "order_value": 137,
        "ath_diff": null,
        "expected_days": 0.3,
        "buy_to_failure": 0
    },
    {
        "name": "تاصیکو3",
        "queue_order_count": 90,
        "total_queue_value": 5.3,
        "solid": true,
        "growth": 1.13,
        "demand_ratio": 1.2,
        "vol_ratio": 0.01,
        "market": 132.3,
        "group": "استخراج کانه های فلزی",
        "pe_ttm": 17.7,
        "chance": 0.07,
        "days_lock": 8,
        "base_vol_percent": 100,
        "recent_growth": 1.15,
        "buy_power": -1.0,
        "each_person_buy": 9,
        "free_float_share": 15,
        "order_value": 138,
        "ath_diff": null,
        "expected_days": 120.0,
        "buy_to_failure": 44
    },
    {
        "name": "ساروم3",
        "queue_order_count": 87,
        "total_queue_value": 26.4,
        "solid": false,
        "growth": 1.02,
        "demand_ratio": 5682.7,
        "vol_ratio": 0.0,
        "market": 17.5,
        "group": "سیمان، آهک و گچ",
        "pe_ttm": 5.9,
        "chance": 0.0,
        "days_lock": 1,
        "base_vol_percent": 100,
        "recent_growth": 1.02,
        "buy_power": 0,
        "each_person_buy": 0,
        "free_float_share": 25,
        "order_value": 873,
        "ath_diff": null,
        "expected_days": 1,
        "buy_to_failure": 0
    },
    {
        "name": "غشوکو",
        "queue_order_count": 84,
        "total_queue_value": 22.6,
        "solid": true,
        "growth": 1.88,
        "demand_ratio": 9.9,
        "vol_ratio": 0.76,
        "market": 0.7,
        "group": "محصولات غذایی و آشامیدنی به جز قند و شکر",
        "pe_ttm": 8.4,
        "chance": 0.07,
        "days_lock": 16,
        "base_vol_percent": 62,
        "recent_growth": 1.53,
        "buy_power": 79.5,
        "each_person_buy": 259,
        "free_float_share": 31,
        "order_value": 144,
        "ath_diff": null,
        "expected_days": 13.0,
        "buy_to_failure": 14
    },
    {
        "name": "شاروم",
        "queue_order_count": 80,
        "total_queue_value": 2.3,
        "solid": false,
        "growth": 2.43,
        "demand_ratio": 0.3,
        "vol_ratio": 1.15,
        "market": 2.6,
        "group": "محصولات شیمیایی",
        "pe_ttm": 13.0,
        "chance": 5.67,
        "days_lock": 3,
        "base_vol_percent": 100,
        "recent_growth": 1.57,
        "buy_power": 4.2,
        "each_person_buy": 55,
        "free_float_share": 30,
        "order_value": 132,
        "ath_diff": null,
        "expected_days": 0.3,
        "buy_to_failure": 0
    },
    {
        "name": "میدکو",
        "queue_order_count": 79,
        "total_queue_value": 10.8,
        "solid": false,
        "growth": 1.98,
        "demand_ratio": 0.3,
        "vol_ratio": 1.05,
        "market": 206.8,
        "group": "فلزات اساسی",
        "pe_ttm": 76.7,
        "chance": 63.82,
        "days_lock": 1,
        "base_vol_percent": 100,
        "recent_growth": 1.32,
        "buy_power": 2.4,
        "each_person_buy": 79,
        "free_float_share": 20,
        "order_value": 142,
        "ath_diff": null,
        "expected_days": 0.3,
        "buy_to_failure": 0
    },
    {
        "name": "کیمیاتک3",
        "queue_order_count": 78,
        "total_queue_value": 7.8,
        "solid": true,
        "growth": 1.0,
        "demand_ratio": 2904.5,
        "vol_ratio": 1.97,
        "market": 16.2,
        "group": "محصولات شیمیایی",
        "pe_ttm": 7.3,
        "chance": 0.02,
        "days_lock": 2,
        "base_vol_percent": 100,
        "recent_growth": 0.99,
        "buy_power": -1.0,
        "each_person_buy": 5,
        "free_float_share": 13,
        "order_value": 108,
        "ath_diff": null,
        "expected_days": 1474.4,
        "buy_to_failure": 98
    },
    {
        "name": "زفارس",
        "queue_order_count": 77,
        "total_queue_value": 3.4,
        "solid": false,
        "growth": 1.75,
        "demand_ratio": 0.3,
        "vol_ratio": 1.58,
        "market": 2.4,
        "group": "زراعت و خدمات وابسته",
        "pe_ttm": 6.3,
        "chance": 1.61,
        "days_lock": 19,
        "base_vol_percent": 100,
        "recent_growth": 1.72,
        "buy_power": 9.1,
        "each_person_buy": 98,
        "free_float_share": 21,
        "order_value": 169,
        "ath_diff": null,
        "expected_days": 0.2,
        "buy_to_failure": 0
    },
    {
        "name": "فسبزوار3",
        "queue_order_count": 77,
        "total_queue_value": 7.8,
        "solid": true,
        "growth": 1.14,
        "demand_ratio": 114.7,
        "vol_ratio": 0.02,
        "market": 20.2,
        "group": "فلزات اساسی",
        "pe_ttm": 3.8,
        "chance": 0.0,
        "days_lock": 7,
        "base_vol_percent": 100,
        "recent_growth": 1.13,
        "buy_power": -1.0,
        "each_person_buy": 2,
        "free_float_share": 16,
        "order_value": 505,
        "ath_diff": null,
        "expected_days": 5735.0,
        "buy_to_failure": 0
    },
    {
        "name": "ثعتما",
        "queue_order_count": 75,
        "total_queue_value": 9.0,
        "solid": false,
        "growth": 1.23,
        "demand_ratio": 4.1,
        "vol_ratio": 0.28,
        "market": 0.4,
        "group": "انبوه سازی، املاک و مستغلات",
        "pe_ttm": -154.3,
        "chance": 90.15,
        "days_lock": 3,
        "base_vol_percent": 100,
        "recent_growth": 1.19,
        "buy_power": 1.1,
        "each_person_buy": 44,
        "free_float_share": 39,
        "order_value": 251,
        "ath_diff": null,
        "expected_days": 14.6,
        "buy_to_failure": 0
    },
    {
        "name": "حخزر",
        "queue_order_count": 75,
        "total_queue_value": 13.9,
        "solid": false,
        "growth": 3.01,
        "demand_ratio": 0.8,
        "vol_ratio": 5.27,
        "market": 6.9,
        "group": "حمل و نقل آبی",
        "pe_ttm": 5.4,
        "chance": 3.86,
        "days_lock": 7,
        "base_vol_percent": 100,
        "recent_growth": 1.76,
        "buy_power": -1.5,
        "each_person_buy": 118,
        "free_float_share": 11,
        "order_value": 108,
        "ath_diff": null,
        "expected_days": 0.2,
        "buy_to_failure": 0
    },
    {
        "name": "سشرق3",
        "queue_order_count": 75,
        "total_queue_value": 9.6,
        "solid": false,
        "growth": 0.95,
        "demand_ratio": 14056.5,
        "vol_ratio": 0.0,
        "market": 11.6,
        "group": "سیمان، آهک و گچ",
        "pe_ttm": 6.4,
        "chance": 0.0,
        "days_lock": 1,
        "base_vol_percent": 100,
        "recent_growth": 1.03,
        "buy_power": 0,
        "each_person_buy": 0,
        "free_float_share": 37,
        "order_value": 186,
        "ath_diff": null,
        "expected_days": 1,
        "buy_to_failure": 0
    },
    {
        "name": "ونوین",
        "queue_order_count": 75,
        "total_queue_value": 5.4,
        "solid": false,
        "growth": 2.08,
        "demand_ratio": 0.0,
        "vol_ratio": 3.64,
        "market": 91.1,
        "group": "بانکها و موسسات اعتباری",
        "pe_ttm": 4.8,
        "chance": 1437.29,
        "days_lock": 1,
        "base_vol_percent": 100,
        "recent_growth": 1.79,
        "buy_power": -1.5,
        "each_person_buy": 176,
        "free_float_share": 32,
        "order_value": 149,
        "ath_diff": null,
        "expected_days": 0.0,
        "buy_to_failure": 0
    },
    {
        "name": "فنر",
        "queue_order_count": 72,
        "total_queue_value": 9.3,
        "solid": true,
        "growth": 1.68,
        "demand_ratio": 1.9,
        "vol_ratio": 1.99,
        "market": 2.5,
        "group": "خودرو و ساخت قطعات",
        "pe_ttm": 6.5,
        "chance": 1.19,
        "days_lock": 4,
        "base_vol_percent": 100,
        "recent_growth": 1.54,
        "buy_power": 9.0,
        "each_person_buy": 232,
        "free_float_share": 10,
        "order_value": 154,
        "ath_diff": null,
        "expected_days": 1.0,
        "buy_to_failure": 0
    },
    {
        "name": "کوچین3",
        "queue_order_count": 69,
        "total_queue_value": 9.2,
        "solid": true,
        "growth": 1.02,
        "demand_ratio": 694.3,
        "vol_ratio": 0.45,
        "market": 9.2,
        "group": "محصولات غذایی و آشامیدنی به جز قند و شکر",
        "pe_ttm": 7.7,
        "chance": 0.02,
        "days_lock": 2,
        "base_vol_percent": 100,
        "recent_growth": 1.05,
        "buy_power": 13.0,
        "each_person_buy": 6,
        "free_float_share": 15,
        "order_value": 116,
        "ath_diff": null,
        "expected_days": 1542.9,
        "buy_to_failure": 110
    },
    {
        "name": "ولراز",
        "queue_order_count": 68,
        "total_queue_value": 8.7,
        "solid": true,
        "growth": 1.29,
        "demand_ratio": 4.8,
        "vol_ratio": 0.04,
        "market": 0.3,
        "group": "سایر واسطه گریهای مالی",
        "pe_ttm": 6.8,
        "chance": 0.0,
        "days_lock": 4,
        "base_vol_percent": 100,
        "recent_growth": 1.21,
        "buy_power": 6.0,
        "each_person_buy": 67,
        "free_float_share": 38,
        "order_value": 75,
        "ath_diff": null,
        "expected_days": 120.0,
        "buy_to_failure": 0
    },
    {
        "name": "بورس3",
        "queue_order_count": 66,
        "total_queue_value": 10.2,
        "solid": false,
        "growth": 1.34,
        "demand_ratio": 180.0,
        "vol_ratio": 0.0,
        "market": 12.8,
        "group": "فعالیتهای کمکی به نهادهای مالی واسط",
        "pe_ttm": 19.0,
        "chance": 0.0,
        "days_lock": 3,
        "base_vol_percent": 100,
        "recent_growth": 1.34,
        "buy_power": 0,
        "each_person_buy": 0,
        "free_float_share": 47,
        "order_value": 106,
        "ath_diff": null,
        "expected_days": 1,
        "buy_to_failure": 0
    },
    {
        "name": "اکتان",
        "queue_order_count": 64,
        "total_queue_value": 2.1,
        "solid": false,
        "growth": 1.91,
        "demand_ratio": 0.2,
        "vol_ratio": 9.93,
        "market": 2.2,
        "group": "صندوق سرمایه گذاری قابل معامله",
        "pe_ttm": 0.0,
        "chance": 1.49,
        "days_lock": 5,
        "base_vol_percent": 100,
        "recent_growth": 1.13,
        "buy_power": -1.2,
        "each_person_buy": 135,
        "free_float_share": 29,
        "order_value": 221,
        "ath_diff": null,
        "expected_days": 0.0,
        "buy_to_failure": 0
    },
    {
        "name": "حبندر",
        "queue_order_count": 64,
        "total_queue_value": 6.6,
        "solid": true,
        "growth": 1.53,
        "demand_ratio": 2.1,
        "vol_ratio": 1.3,
        "market": 2.4,
        "group": "حمل ونقل، انبارداری و ارتباطات",
        "pe_ttm": 8.9,
        "chance": 0.35,
        "days_lock": 8,
        "base_vol_percent": 75,
        "recent_growth": 1.58,
        "buy_power": 1.4,
        "each_person_buy": 213,
        "free_float_share": 25,
        "order_value": 158,
        "ath_diff": null,
        "expected_days": 1.6,
        "buy_to_failure": 58
    },
    {
        "name": "صبا3",
        "queue_order_count": 63,
        "total_queue_value": 5.5,
        "solid": true,
        "growth": 1.18,
        "demand_ratio": 6.6,
        "vol_ratio": 0.0,
        "market": 55.8,
        "group": "سرمایه گذاریها",
        "pe_ttm": 6.0,
        "chance": 0.5,
        "days_lock": 5,
        "base_vol_percent": 100,
        "recent_growth": 1.18,
        "buy_power": -1.0,
        "each_person_buy": 2,
        "free_float_share": 13,
        "order_value": 194,
        "ath_diff": null,
        "expected_days": 1,
        "buy_to_failure": 100
    },
    {
        "name": "شکام",
        "queue_order_count": 62,
        "total_queue_value": 5.6,
        "solid": false,
        "growth": 2.17,
        "demand_ratio": 0.1,
        "vol_ratio": 1.59,
        "market": 9.8,
        "group": "محصولات شیمیایی",
        "pe_ttm": 5.6,
        "chance": 84.65,
        "days_lock": 1,
        "base_vol_percent": 100,
        "recent_growth": 1.65,
        "buy_power": 1.0,
        "each_person_buy": 113,
        "free_float_share": 31,
        "order_value": 112,
        "ath_diff": null,
        "expected_days": 0.1,
        "buy_to_failure": 0
    },
    {
        "name": "تاپکیش",
        "queue_order_count": 62,
        "total_queue_value": 7.8,
        "solid": false,
        "growth": 2.54,
        "demand_ratio": 0.6,
        "vol_ratio": 2.84,
        "market": 1.8,
        "group": "رایانه و فعالیتهای وابسته به آن",
        "pe_ttm": 24.7,
        "chance": 266.66,
        "days_lock": 2,
        "base_vol_percent": 100,
        "recent_growth": 1.14,
        "buy_power": 3.0,
        "each_person_buy": 524,
        "free_float_share": 28,
        "order_value": 142,
        "ath_diff": null,
        "expected_days": 0.2,
        "buy_to_failure": 0
    },
    {
        "name": "بوعلی3",
        "queue_order_count": 61,
        "total_queue_value": 5.0,
        "solid": true,
        "growth": 1.06,
        "demand_ratio": 15.9,
        "vol_ratio": 0.0,
        "market": 62.0,
        "group": "محصولات شیمیایی",
        "pe_ttm": 8.4,
        "chance": 0.01,
        "days_lock": 5,
        "base_vol_percent": 100,
        "recent_growth": 1.09,
        "buy_power": -2.0,
        "each_person_buy": 0,
        "free_float_share": 39,
        "order_value": 308,
        "ath_diff": null,
        "expected_days": 1,
        "buy_to_failure": 3
    },
    {
        "name": "کیسون",
        "queue_order_count": 61,
        "total_queue_value": 2.6,
        "solid": false,
        "growth": 1.32,
        "demand_ratio": 0.1,
        "vol_ratio": 1.14,
        "market": 4.1,
        "group": "خدمات فنی و مهندسی",
        "pe_ttm": 7.8,
        "chance": 11.02,
        "days_lock": 2,
        "base_vol_percent": 100,
        "recent_growth": 1.28,
        "buy_power": 1.3,
        "each_person_buy": 91,
        "free_float_share": 48,
        "order_value": 59,
        "ath_diff": null,
        "expected_days": 0.1,
        "buy_to_failure": 0
    },
    {
        "name": "سخواف",
        "queue_order_count": 61,
        "total_queue_value": 5.7,
        "solid": true,
        "growth": 3.2,
        "demand_ratio": 10.2,
        "vol_ratio": 1.87,
        "market": 1.3,
        "group": "سیمان، آهک و گچ",
        "pe_ttm": -64.2,
        "chance": 0.11,
        "days_lock": 23,
        "base_vol_percent": 26,
        "recent_growth": 1.51,
        "buy_power": 5.8,
        "each_person_buy": 144,
        "free_float_share": 70,
        "order_value": 177,
        "ath_diff": null,
        "expected_days": 5.5,
        "buy_to_failure": 23
    },
    {
        "name": "غمهرا3",
        "queue_order_count": 60,
        "total_queue_value": 7.3,
        "solid": true,
        "growth": 1.01,
        "demand_ratio": 14130.9,
        "vol_ratio": 2.45,
        "market": 7.4,
        "group": "محصولات غذایی و آشامیدنی به جز قند و شکر",
        "pe_ttm": 8.2,
        "chance": 0.0,
        "days_lock": 2,
        "base_vol_percent": 100,
        "recent_growth": 1.01,
        "buy_power": -1.0,
        "each_person_buy": 1,
        "free_float_share": 27,
        "order_value": 147,
        "ath_diff": null,
        "expected_days": 5767.7,
        "buy_to_failure": 0
    },
    {
        "name": "شمواد",
        "queue_order_count": 60,
        "total_queue_value": 4.7,
        "solid": false,
        "growth": 3.42,
        "demand_ratio": 0.2,
        "vol_ratio": 1.25,
        "market": 4.8,
        "group": "محصولات شیمیایی",
        "pe_ttm": 5.2,
        "chance": 670.67,
        "days_lock": 1,
        "base_vol_percent": 100,
        "recent_growth": 1.75,
        "buy_power": 1.0,
        "each_person_buy": 155,
        "free_float_share": 38,
        "order_value": 144,
        "ath_diff": null,
        "expected_days": 0.2,
        "buy_to_failure": 0
    },
    {
        "name": "شپدیس3",
        "queue_order_count": 60,
        "total_queue_value": 1.5,
        "solid": true,
        "growth": 1.0,
        "demand_ratio": 0.3,
        "vol_ratio": 0.04,
        "market": 292.9,
        "group": "محصولات شیمیایی",
        "pe_ttm": 6.1,
        "chance": 1.38,
        "days_lock": 11,
        "base_vol_percent": 100,
        "recent_growth": 0.95,
        "buy_power": 1.7,
        "each_person_buy": 35,
        "free_float_share": 14,
        "order_value": 125,
        "ath_diff": null,
        "expected_days": 7.5,
        "buy_to_failure": 0
    },
    {
        "name": "دلقما3",
        "queue_order_count": 60,
        "total_queue_value": 6.8,
        "solid": false,
        "growth": 0,
        "demand_ratio": 0,
        "vol_ratio": 0,
        "market": 3.9,
        "group": "مواد و محصولات دارویی",
        "pe_ttm": 6.1,
        "chance": 0.0,
        "days_lock": 0,
        "base_vol_percent": 0,
        "recent_growth": 0,
        "buy_power": 27,
        "each_person_buy": 151,
        "free_float_share": null,
        "order_value": 1,
        "buy_to_failure": 0
    },
    {
        "name": "نیروترانسفو",
        "queue_order_count": 57,
        "total_queue_value": 2.2,
        "solid": false,
        "growth": 1.94,
        "demand_ratio": 0.1,
        "vol_ratio": 3.29,
        "market": 4.7,
        "group": "ماشین آلات و دستگاههای برقی",
        "pe_ttm": 7.9,
        "chance": 31.02,
        "days_lock": 22,
        "base_vol_percent": 100,
        "recent_growth": 1.72,
        "buy_power": 14.1,
        "each_person_buy": 44,
        "free_float_share": 15,
        "order_value": 156,
        "ath_diff": null,
        "expected_days": 0.0,
        "buy_to_failure": 0
    },
    {
        "name": "زاگرس",
        "queue_order_count": 56,
        "total_queue_value": 1.7,
        "solid": false,
        "growth": 1.64,
        "demand_ratio": 0.1,
        "vol_ratio": 3.51,
        "market": 29.4,
        "group": "محصولات شیمیایی",
        "pe_ttm": 18.1,
        "chance": 236.81,
        "days_lock": 1,
        "base_vol_percent": 100,
        "recent_growth": 1.2,
        "buy_power": 1.1,
        "each_person_buy": 85,
        "free_float_share": 10,
        "order_value": 611,
        "ath_diff": null,
        "expected_days": 0.0,
        "buy_to_failure": 0
    },
    {
        "name": "شکلر3",
        "queue_order_count": 56,
        "total_queue_value": 9.2,
        "solid": true,
        "growth": 1.12,
        "demand_ratio": 346.7,
        "vol_ratio": 0.14,
        "market": 7.7,
        "group": "محصولات شیمیایی",
        "pe_ttm": 6.5,
        "chance": 0.01,
        "days_lock": 5,
        "base_vol_percent": 100,
        "recent_growth": 1.15,
        "buy_power": -1.0,
        "each_person_buy": 4,
        "free_float_share": 21,
        "order_value": 191,
        "ath_diff": null,
        "expected_days": 2476.4,
        "buy_to_failure": 144
    },
    {
        "name": "شاملا3",
        "queue_order_count": 56,
        "total_queue_value": 12.2,
        "solid": true,
        "growth": 1.0,
        "demand_ratio": 11.8,
        "vol_ratio": 0.0,
        "market": 13.1,
        "group": "محصولات شیمیایی",
        "pe_ttm": 8.7,
        "chance": 0.0,
        "days_lock": 6,
        "base_vol_percent": 100,
        "recent_growth": 0.96,
        "buy_power": -1.0,
        "each_person_buy": 1,
        "free_float_share": 23,
        "order_value": 261,
        "ath_diff": null,
        "expected_days": 1,
        "buy_to_failure": 0
    },
    {
        "name": "دلر3",
        "queue_order_count": 55,
        "total_queue_value": 7.5,
        "solid": false,
        "growth": 0,
        "demand_ratio": 0,
        "vol_ratio": 0,
        "market": 13.8,
        "group": "مواد و محصولات دارویی",
        "pe_ttm": 8.9,
        "chance": 0.0,
        "days_lock": 0,
        "base_vol_percent": 0,
        "recent_growth": 0,
        "buy_power": 17,
        "each_person_buy": 149,
        "free_float_share": null,
        "order_value": 1,
        "buy_to_failure": 0
    },
    {
        "name": "وپخش",
        "queue_order_count": 53,
        "total_queue_value": 12.9,
        "solid": false,
        "growth": 3.54,
        "demand_ratio": 1.4,
        "vol_ratio": 9.53,
        "market": 33.9,
        "group": "مواد و محصولات دارویی",
        "pe_ttm": 22.3,
        "chance": 13.3,
        "days_lock": 25,
        "base_vol_percent": 100,
        "recent_growth": 1.84,
        "buy_power": -2.5,
        "each_person_buy": 110,
        "free_float_share": 10,
        "order_value": 403,
        "ath_diff": null,
        "expected_days": 0.1,
        "buy_to_failure": 0
    },
    {
        "name": "خیمن",
        "queue_order_count": 53,
        "total_queue_value": 1.0,
        "solid": true,
        "growth": 1.11,
        "demand_ratio": 0.3,
        "vol_ratio": 1.24,
        "market": 1.9,
        "group": "خودرو و ساخت قطعات",
        "pe_ttm": 3.9,
        "chance": 0.65,
        "days_lock": 7,
        "base_vol_percent": 100,
        "recent_growth": 1.06,
        "buy_power": 35.6,
        "each_person_buy": 416,
        "free_float_share": 17,
        "order_value": 110,
        "ath_diff": null,
        "expected_days": 0.2,
        "buy_to_failure": 72
    },
    {
        "name": "شلرد",
        "queue_order_count": 52,
        "total_queue_value": 6.1,
        "solid": false,
        "growth": 1.67,
        "demand_ratio": 0.3,
        "vol_ratio": 2.21,
        "market": 10.9,
        "group": "محصولات شیمیایی",
        "pe_ttm": 29.0,
        "chance": 78.67,
        "days_lock": 1,
        "base_vol_percent": 100,
        "recent_growth": 1.55,
        "buy_power": 1.3,
        "each_person_buy": 115,
        "free_float_share": 31,
        "order_value": 105,
        "ath_diff": null,
        "expected_days": 0.1,
        "buy_to_failure": 0
    },
    {
        "name": "فرابورس3",
        "queue_order_count": 50,
        "total_queue_value": 9.1,
        "solid": true,
        "growth": 1.3,
        "demand_ratio": 98.8,
        "vol_ratio": 0.51,
        "market": 9.7,
        "group": "فعالیتهای کمکی به نهادهای مالی واسط",
        "pe_ttm": 18.2,
        "chance": 0.05,
        "days_lock": 9,
        "base_vol_percent": 100,
        "recent_growth": 1.29,
        "buy_power": -1.0,
        "each_person_buy": 47,
        "free_float_share": 52,
        "order_value": 122,
        "ath_diff": null,
        "expected_days": 193.7,
        "buy_to_failure": 42
    },
    {
        "name": "دزاگرس3",
        "queue_order_count": 50,
        "total_queue_value": 3.9,
        "solid": true,
        "growth": 1.29,
        "demand_ratio": 2.2,
        "vol_ratio": 0.03,
        "market": 12.4,
        "group": "مواد و محصولات دارویی",
        "pe_ttm": 8.8,
        "chance": 0.37,
        "days_lock": 6,
        "base_vol_percent": 100,
        "recent_growth": 1.33,
        "buy_power": 9.0,
        "each_person_buy": 60,
        "free_float_share": 27,
        "order_value": 160,
        "ath_diff": null,
        "expected_days": 73.3,
        "buy_to_failure": 189
    },
    {
        "name": "وپخش3",
        "queue_order_count": 50,
        "total_queue_value": 17.2,
        "solid": false,
        "growth": 1.02,
        "demand_ratio": 861291.9,
        "vol_ratio": 0.0,
        "market": 33.5,
        "group": "مواد و محصولات دارویی",
        "pe_ttm": 22.0,
        "chance": 0.0,
        "days_lock": 1,
        "base_vol_percent": 100,
        "recent_growth": 1.03,
        "buy_power": 0,
        "each_person_buy": 0,
        "free_float_share": 10,
        "order_value": 399,
        "ath_diff": null,
        "expected_days": 1,
        "buy_to_failure": 0
    },
    {
        "name": "کیمیا",
        "queue_order_count": 49,
        "total_queue_value": 2.5,
        "solid": false,
        "growth": 1.76,
        "demand_ratio": 0.7,
        "vol_ratio": 7.21,
        "market": 1.5,
        "group": "فلزات اساسی",
        "pe_ttm": 3.8,
        "chance": 1.83,
        "days_lock": 8,
        "base_vol_percent": 100,
        "recent_growth": 1.68,
        "buy_power": -1.2,
        "each_person_buy": 117,
        "free_float_share": 36,
        "order_value": 119,
        "ath_diff": null,
        "expected_days": 0.1,
        "buy_to_failure": 0
    },
    {
        "name": "غدیس",
        "queue_order_count": 48,
        "total_queue_value": 9.5,
        "solid": false,
        "growth": 2.22,
        "demand_ratio": 0.4,
        "vol_ratio": 1.92,
        "market": 5.6,
        "group": "محصولات غذایی و آشامیدنی به جز قند و شکر",
        "pe_ttm": 6.6,
        "chance": 419.72,
        "days_lock": 1,
        "base_vol_percent": 100,
        "recent_growth": 1.78,
        "buy_power": -2.0,
        "each_person_buy": 59,
        "free_float_share": 31,
        "order_value": 481,
        "ath_diff": null,
        "expected_days": 0.2,
        "buy_to_failure": 0
    },
    {
        "name": "فصبا",
        "queue_order_count": 48,
        "total_queue_value": 3.4,
        "solid": false,
        "growth": 1.41,
        "demand_ratio": 0.4,
        "vol_ratio": 1.53,
        "market": 14.3,
        "group": "فلزات اساسی",
        "pe_ttm": 8.0,
        "chance": 3704.37,
        "days_lock": 1,
        "base_vol_percent": 100,
        "recent_growth": 1.41,
        "buy_power": 5.5,
        "each_person_buy": 85,
        "free_float_share": 12,
        "order_value": 114,
        "ath_diff": null,
        "expected_days": 0.3,
        "buy_to_failure": 0
    },
    {
        "name": "نیروترانسفو3",
        "queue_order_count": 47,
        "total_queue_value": 2.6,
        "solid": true,
        "growth": 1.21,
        "demand_ratio": 249.4,
        "vol_ratio": 1.45,
        "market": 4.5,
        "group": "ماشین آلات و دستگاههای برقی",
        "pe_ttm": 7.6,
        "chance": 0.9,
        "days_lock": 3,
        "base_vol_percent": 100,
        "recent_growth": 1.24,
        "buy_power": 46.0,
        "each_person_buy": 15,
        "free_float_share": 15,
        "order_value": 150,
        "ath_diff": null,
        "expected_days": 172.0,
        "buy_to_failure": 0
    },
    {
        "name": "مالک آتیه",
        "queue_order_count": 47,
        "total_queue_value": 3.3,
        "solid": false,
        "growth": 1.2,
        "demand_ratio": 0.1,
        "vol_ratio": 4.22,
        "market": 0.6,
        "group": "صندوق سرمایه گذاری قابل معامله",
        "pe_ttm": 714.4,
        "chance": 304.42,
        "days_lock": 1,
        "base_vol_percent": 100,
        "recent_growth": 0.79,
        "buy_power": 1.2,
        "each_person_buy": 235,
        "free_float_share": 20,
        "order_value": 120,
        "ath_diff": null,
        "expected_days": 0.0,
        "buy_to_failure": 0
    },
    {
        "name": "وپست3",
        "queue_order_count": 45,
        "total_queue_value": 4.9,
        "solid": true,
        "growth": 1.18,
        "demand_ratio": 209.4,
        "vol_ratio": 0.02,
        "market": 44.5,
        "group": "بانکها و موسسات اعتباری",
        "pe_ttm": 4.7,
        "chance": 0.03,
        "days_lock": 5,
        "base_vol_percent": 100,
        "recent_growth": 1.15,
        "buy_power": -1.0,
        "each_person_buy": 0,
        "free_float_share": 36,
        "order_value": 179,
        "ath_diff": null,
        "expected_days": 10470.0,
        "buy_to_failure": 1692
    },
    {
        "name": "پارسان3",
        "queue_order_count": 45,
        "total_queue_value": 6.1,
        "solid": true,
        "growth": 1.0,
        "demand_ratio": 16.3,
        "vol_ratio": 1.91,
        "market": 341.5,
        "group": "محصولات شیمیایی",
        "pe_ttm": 16.8,
        "chance": 3.17,
        "days_lock": 9,
        "base_vol_percent": 100,
        "recent_growth": 1.04,
        "buy_power": -2.3,
        "each_person_buy": 102,
        "free_float_share": 9,
        "order_value": 281,
        "ath_diff": null,
        "expected_days": 8.5,
        "buy_to_failure": 0
    },
    {
        "name": "برکت3",
        "queue_order_count": 43,
        "total_queue_value": 2.6,
        "solid": true,
        "growth": 1.16,
        "demand_ratio": 131.6,
        "vol_ratio": 3.88,
        "market": 5.9,
        "group": "مواد و محصولات دارویی",
        "pe_ttm": 242.1,
        "chance": 0.55,
        "days_lock": 5,
        "base_vol_percent": 100,
        "recent_growth": 1.16,
        "buy_power": 3.0,
        "each_person_buy": 38,
        "free_float_share": 33,
        "order_value": 135,
        "ath_diff": null,
        "expected_days": 33.9,
        "buy_to_failure": 150
    },
    {
        "name": "فن افزار3",
        "queue_order_count": 42,
        "total_queue_value": 4.7,
        "solid": true,
        "growth": 1.06,
        "demand_ratio": 2360.9,
        "vol_ratio": 0.13,
        "market": 2.4,
        "group": "رایانه و فعالیتهای وابسته به آن",
        "pe_ttm": 3.1,
        "chance": 0.0,
        "days_lock": 7,
        "base_vol_percent": 100,
        "recent_growth": 1.09,
        "buy_power": 2.0,
        "each_person_buy": 0,
        "free_float_share": 38,
        "order_value": 158,
        "ath_diff": null,
        "expected_days": 18160.8,
        "buy_to_failure": 0
    },
    {
        "name": "البرز3",
        "queue_order_count": 42,
        "total_queue_value": 3.7,
        "solid": false,
        "growth": 1.01,
        "demand_ratio": 1134.4,
        "vol_ratio": 0.0,
        "market": 18.0,
        "group": "بیمه وصندوق بازنشستگی به جزتامین اجتماعی",
        "pe_ttm": 2.9,
        "chance": 0.0,
        "days_lock": 4,
        "base_vol_percent": 100,
        "recent_growth": 0.93,
        "buy_power": 0,
        "each_person_buy": 0,
        "free_float_share": 11,
        "order_value": 87,
        "ath_diff": null,
        "expected_days": 1,
        "buy_to_failure": 0
    },
    {
        "name": "جوین",
        "queue_order_count": 42,
        "total_queue_value": 1.8,
        "solid": false,
        "growth": 1.71,
        "demand_ratio": 0.4,
        "vol_ratio": 5.84,
        "market": 7.0,
        "group": "زراعت و خدمات وابسته",
        "pe_ttm": 6.1,
        "chance": 4.76,
        "days_lock": 24,
        "base_vol_percent": 20,
        "recent_growth": 1.53,
        "buy_power": 1.1,
        "each_person_buy": 97,
        "free_float_share": 51,
        "order_value": 187,
        "ath_diff": null,
        "expected_days": 0.1,
        "buy_to_failure": 0
    },
    {
        "name": "کسعدی",
        "queue_order_count": 41,
        "total_queue_value": 3.0,
        "solid": false,
        "growth": 2.28,
        "demand_ratio": 0.2,
        "vol_ratio": 0.92,
        "market": 1.2,
        "group": "کاشی و سرامیک",
        "pe_ttm": 9.7,
        "chance": 20.59,
        "days_lock": 1,
        "base_vol_percent": 100,
        "recent_growth": 1.56,
        "buy_power": 3.3,
        "each_person_buy": 249,
        "free_float_share": 39,
        "order_value": 116,
        "ath_diff": null,
        "expected_days": 0.2,
        "buy_to_failure": 0
    }
]